<?xml version="1.0" encoding="UTF-8"?>
<?xml-model href="../../schemata/tei_all.rnc" type="application/relax-ng-compact-syntax"?>
<tei:TEI xmlns:tei="http://www.tei-c.org/ns/1.0" xmlns:xsd="http://www.w3.org/2001/XMLSchema" xmlns:mhdbdb="http://www.dhplus.sbg.ac.at/mhdbdb/" xml:id="BMG">
  <tei:teiHeader>
            <tei:fileDesc>
                <tei:titleStmt>
                    <tei:title>BMG</tei:title>
                </tei:titleStmt>
                <tei:publicationStmt>
                    <tei:p>
                        Dieser Header ist ein Platzhalter zur Validierung der Datei. 
                        Der Eigentliche Header wird aus den RDF-Daten erzeugt werden.
                    </tei:p>
                </tei:publicationStmt>
                <tei:sourceDesc>
                    <tei:p>MHDBDB</tei:p>
                </tei:sourceDesc>
            </tei:fileDesc>
        </tei:teiHeader>
  <tei:text>
    <tei:body>
      <tei:p resp="Generated by Export-Script">
        <tei:l n="1">
          <tei:seg xml:id="BMG_16100010_0" type="token">himels</tei:seg>
          <tei:seg xml:id="BMG_16100010_1" type="token">unt</tei:seg>
          <tei:seg xml:id="BMG_16100010_2" type="token">erde</tei:seg>
          <tei:seg xml:id="BMG_16100010_3" type="token">schepfære</tei:seg>
          <tei:seg xml:id="BMG_16100010_4" type="pc">,</tei:seg>
        </tei:l>
        <tei:l n="2">
          <tei:seg xml:id="BMG_16100020_0" type="token">sit</tei:seg>
          <tei:seg xml:id="BMG_16100020_1" type="token">du</tei:seg>
          <tei:seg xml:id="BMG_16100020_2" type="token">den</tei:seg>
          <tei:seg xml:id="BMG_16100020_3" type="token">froude</tei:seg>
          <tei:seg xml:id="BMG_16100020_4" type="token">bære</tei:seg>
          <tei:seg xml:id="BMG_16100020_5" type="pc">,</tei:seg>
        </tei:l>
        <tei:l n="3">
          <tei:seg xml:id="BMG_16100030_0" type="token">die</tei:seg>
          <tei:seg xml:id="BMG_16100030_1" type="token">ze</tei:seg>
          <tei:seg xml:id="BMG_16100030_2" type="token">helle</tei:seg>
          <tei:seg xml:id="BMG_16100030_3" type="token">gevarn</tei:seg>
          <tei:seg xml:id="BMG_16100030_4" type="token">waren</tei:seg>
        </tei:l>
        <tei:l n="4">
          <tei:seg xml:id="BMG_16100040_0" type="token">und</tei:seg>
          <tei:seg xml:id="BMG_16100040_1" type="token">lange</tei:seg>
          <tei:seg xml:id="BMG_16100040_2" type="token">froude</tei:seg>
          <tei:seg xml:id="BMG_16100040_3" type="token">enbaren</tei:seg>
        </tei:l>
        <tei:l n="5">
          <tei:seg xml:id="BMG_16100050_0" type="token">-</tei:seg>
          <tei:seg xml:id="BMG_16100050_1" type="token">die</tei:seg>
          <tei:seg xml:id="BMG_16100050_2" type="token">gnussen</tei:seg>
          <tei:seg xml:id="BMG_16100050_3" type="token">diner</tei:seg>
          <tei:seg xml:id="BMG_16100050_4" type="token">urstende</tei:seg>
          <tei:seg xml:id="BMG_16100050_5" type="token">-</tei:seg>
          <tei:seg xml:id="BMG_16100050_6" type="pc">,</tei:seg>
        </tei:l>
        <tei:l n="6">
          <tei:seg xml:id="BMG_16100060_0" type="token">also</tei:seg>
          <tei:seg xml:id="BMG_16100060_1" type="token">mache</tei:seg>
          <tei:seg xml:id="BMG_16100060_2" type="pc">,</tei:seg>
          <tei:seg xml:id="BMG_16100060_3" type="token">herre</tei:seg>
          <tei:seg xml:id="BMG_16100060_4" type="pc">,</tei:seg>
          <tei:seg xml:id="BMG_16100060_5" type="token">ein</tei:seg>
          <tei:seg xml:id="BMG_16100060_6" type="token">ende</tei:seg>
        </tei:l>
        <tei:l n="7">
          <tei:seg xml:id="BMG_16100070_0" type="token">aller</tei:seg>
          <tei:supplied>
            <tei:seg xml:id="BMG_16100070_1" type="token">der</tei:seg>
          </tei:supplied>
          <tei:seg xml:id="BMG_16100070_2" type="token">sunden</tei:seg>
          <tei:seg xml:id="BMG_16100070_3" type="pc">,</tei:seg>
          <tei:seg xml:id="BMG_16100070_4" type="token">die</tei:seg>
          <tei:seg xml:id="BMG_16100070_5" type="token">ich</tei:seg>
          <tei:seg xml:id="BMG_16100070_6" type="token">han</tei:seg>
          <tei:seg xml:id="BMG_16100070_7" type="pc">,</tei:seg>
        </tei:l>
        <tei:l n="8">
          <tei:seg xml:id="BMG_16100080_0" type="token">daz</tei:seg>
          <tei:seg xml:id="BMG_16100080_1" type="token">ich</tei:seg>
          <tei:seg xml:id="BMG_16100080_2" type="token">mit</tei:seg>
          <tei:seg xml:id="BMG_16100080_3" type="token">frouden</tei:seg>
          <tei:seg xml:id="BMG_16100080_4" type="token">muze</tei:seg>
          <tei:seg xml:id="BMG_16100080_5" type="token">erstan</tei:seg>
        </tei:l>
        <tei:l n="9">
          <tei:seg xml:id="BMG_16100090_0" type="token">zeder</tei:seg>
          <tei:seg xml:id="BMG_16100090_1" type="token">urstende</tei:seg>
          <tei:seg xml:id="BMG_16100090_2" type="pc">,</tei:seg>
          <tei:seg xml:id="BMG_16100090_3" type="token">diu</tei:seg>
          <tei:seg xml:id="BMG_16100090_4" type="token">daz</tei:seg>
          <tei:seg xml:id="BMG_16100090_5" type="token">gebirt</tei:seg>
          <tei:seg xml:id="BMG_16100090_6" type="pc">,</tei:seg>
        </tei:l>
        <tei:l n="10">
          <tei:seg xml:id="BMG_16100100_0" type="token">daz</tei:seg>
          <tei:seg xml:id="BMG_16100100_1" type="token">nihtes</tei:seg>
          <tei:seg xml:id="BMG_16100100_2" type="token">da</tei:seg>
          <tei:seg xml:id="BMG_16100100_3" type="token">vergezen</tei:seg>
          <tei:seg xml:id="BMG_16100100_4" type="token">wirt</tei:seg>
          <tei:seg xml:id="BMG_16100100_5" type="pc">!</tei:seg>
        </tei:l>
        <tei:l n="11">
          <tei:seg xml:id="BMG_16100110_0" type="token">daz</tei:seg>
          <tei:seg xml:id="BMG_16100110_1" type="token">min</tei:seg>
          <tei:seg xml:id="BMG_16100110_2" type="token">din</tei:seg>
          <tei:seg xml:id="BMG_16100110_3" type="token">chraft</tei:seg>
          <tei:seg xml:id="BMG_16100110_4" type="token">da</tei:seg>
          <tei:seg xml:id="BMG_16100110_5" type="token">muze</tei:seg>
          <tei:seg xml:id="BMG_16100110_6" type="token">pflegen</tei:seg>
        </tei:l>
        <tei:l n="12">
          <tei:seg xml:id="BMG_16100120_0" type="token">und</tei:seg>
          <tei:seg xml:id="BMG_16100120_1" type="token">din</tei:seg>
          <tei:seg xml:id="BMG_16100120_2" type="token">vil</tei:seg>
          <tei:seg xml:id="BMG_16100120_3" type="token">heiliger</tei:seg>
          <tei:seg xml:id="BMG_16100120_4" type="token">segen</tei:seg>
          <tei:seg xml:id="BMG_16100120_5" type="pc">,</tei:seg>
        </tei:l>
        <tei:l n="13">
          <tei:seg xml:id="BMG_16100130_0" type="token">des</tei:seg>
          <tei:seg xml:id="BMG_16100130_1" type="token">hilf</tei:seg>
          <tei:seg xml:id="BMG_16100130_2" type="token">mir</tei:seg>
          <tei:seg xml:id="BMG_16100130_3" type="token">durch</tei:seg>
          <tei:seg xml:id="BMG_16100130_4" type="token">den</tei:seg>
          <tei:seg xml:id="BMG_16100130_5" type="token">willen</tei:seg>
          <tei:seg xml:id="BMG_16100130_6" type="token">din</tei:seg>
        </tei:l>
        <tei:l n="14">
          <tei:seg xml:id="BMG_16100140_0" type="token">und</tei:seg>
          <tei:seg xml:id="BMG_16100140_1" type="token">durch</tei:seg>
          <tei:seg xml:id="BMG_16100140_2" type="token">alle</tei:seg>
          <tei:seg xml:id="BMG_16100140_3" type="pc">,</tei:seg>
          <tei:seg xml:id="BMG_16100140_4" type="token">die</tei:seg>
          <tei:seg xml:id="BMG_16100140_5" type="token">dir</tei:seg>
          <tei:seg xml:id="BMG_16100140_6" type="token">liep</tei:seg>
          <tei:seg xml:id="BMG_16100140_7" type="token">sin</tei:seg>
          <tei:seg xml:id="BMG_16100140_8" type="pc">!</tei:seg>
        </tei:l>
        <tei:l n="15">
          <tei:seg xml:id="BMG_16100150_0" type="token">nu</tei:seg>
          <tei:seg xml:id="BMG_16100150_1" type="token">gedenche</tei:seg>
          <tei:seg xml:id="BMG_16100150_2" type="pc">,</tei:seg>
          <tei:seg xml:id="BMG_16100150_3" type="token">sant</tei:seg>
          <tei:seg xml:id="BMG_16100150_4" type="token">marien</tei:seg>
          <tei:seg xml:id="BMG_16100150_5" type="token">chint</tei:seg>
          <tei:seg xml:id="BMG_16100150_6" type="pc">,</tei:seg>
        </tei:l>
        <tei:l n="16">
          <tei:seg xml:id="BMG_16100160_0" type="token">wie</tei:seg>
          <tei:seg xml:id="BMG_16100160_1" type="token">groz</tei:seg>
          <tei:seg xml:id="BMG_16100160_2" type="token">diner</tei:seg>
          <tei:seg xml:id="BMG_16100160_3" type="token">muter</tei:seg>
          <tei:seg xml:id="BMG_16100160_4" type="token">triwe</tei:seg>
          <tei:seg xml:id="BMG_16100160_5" type="token">sint</tei:seg>
          <tei:seg xml:id="BMG_16100160_6" type="pc">,</tei:seg>
        </tei:l>
        <tei:l n="17">
          <tei:seg xml:id="BMG_16100170_0" type="token">wie</tei:seg>
          <tei:seg xml:id="BMG_16100170_1" type="token">michel</tei:seg>
          <tei:seg xml:id="BMG_16100170_2" type="token">ir</tei:seg>
          <tei:seg xml:id="BMG_16100170_3" type="token">iamer</tei:seg>
          <tei:seg xml:id="BMG_16100170_4" type="token">wære</tei:seg>
        </tei:l>
        <tei:l n="18">
          <tei:seg xml:id="BMG_16100180_0" type="token">und</tei:seg>
          <tei:seg xml:id="BMG_16100180_1" type="token">aller</tei:seg>
          <tei:seg xml:id="BMG_16100180_2" type="token">diner</tei:seg>
          <tei:seg xml:id="BMG_16100180_3" type="token">minnære</tei:seg>
          <tei:seg xml:id="BMG_16100180_4" type="pc">,</tei:seg>
        </tei:l>
        <tei:l n="19">
          <tei:seg xml:id="BMG_16100190_0" type="token">die</tei:seg>
          <tei:seg xml:id="BMG_16100190_1" type="token">nach</tei:seg>
          <tei:seg xml:id="BMG_16100190_2" type="token">sahen</tei:seg>
          <tei:seg xml:id="BMG_16100190_3" type="token">diner</tei:seg>
          <tei:seg xml:id="BMG_16100190_4" type="token">menschæit</tei:seg>
          <tei:seg xml:id="BMG_16100190_5" type="pc">!</tei:seg>
        </tei:l>
        <tei:l n="20">
          <tei:seg xml:id="BMG_16100200_0" type="token">durch</tei:seg>
          <tei:seg xml:id="BMG_16100200_1" type="token">ir</tei:seg>
          <tei:seg xml:id="BMG_16100200_2" type="token">aller</tei:seg>
          <tei:seg xml:id="BMG_16100200_3" type="token">swære</tei:seg>
          <tei:seg xml:id="BMG_16100200_4" type="token">unt</tei:seg>
          <tei:seg xml:id="BMG_16100200_5" type="token">ir</tei:seg>
          <tei:seg xml:id="BMG_16100200_6" type="token">læit</tei:seg>
          <tei:seg xml:id="BMG_16100200_7" type="pc">,</tei:seg>
        </tei:l>
        <tei:l n="21">
          <tei:seg xml:id="BMG_16100210_0" type="token">la</tei:seg>
          <tei:seg xml:id="BMG_16100210_1" type="token">mich</tei:seg>
          <tei:seg xml:id="BMG_16100210_2" type="token">von</tei:seg>
          <tei:seg xml:id="BMG_16100210_3" type="token">dinen</tei:seg>
          <tei:seg xml:id="BMG_16100210_4" type="token">gnaden</tei:seg>
          <tei:seg xml:id="BMG_16100210_5" type="token">niht</tei:seg>
        </tei:l>
        <tei:l n="22">
          <tei:seg xml:id="BMG_16100220_0" type="token">und</tei:seg>
          <tei:seg xml:id="BMG_16100220_1" type="token">erbarme</tei:seg>
          <tei:seg xml:id="BMG_16100220_2" type="token">dich</tei:seg>
          <tei:supplied>
            <tei:seg xml:id="BMG_16100220_3" type="token">uber</tei:seg>
          </tei:supplied>
          <tei:seg xml:id="BMG_16100220_4" type="token">die</tei:seg>
          <tei:seg xml:id="BMG_16100220_5" type="token">gesiht</tei:seg>
          <tei:seg xml:id="BMG_16100220_6" type="pc">,</tei:seg>
        </tei:l>
        <tei:l n="23">
          <tei:seg xml:id="BMG_16100230_0" type="token">die</tei:seg>
          <tei:seg xml:id="BMG_16100230_1" type="token">ich</tei:seg>
          <tei:seg xml:id="BMG_16100230_2" type="token">nach</tei:seg>
          <tei:seg xml:id="BMG_16100230_3" type="token">dir</tei:seg>
          <tei:seg xml:id="BMG_16100230_4" type="token">sihe</tei:seg>
          <tei:seg xml:id="BMG_16100230_5" type="token">tougen</tei:seg>
        </tei:l>
        <tei:l n="24">
          <tei:seg xml:id="BMG_16100240_0" type="token">mit</tei:seg>
          <tei:seg xml:id="BMG_16100240_1" type="token">hercen</tei:seg>
          <tei:seg xml:id="BMG_16100240_2" type="token">unt</tei:seg>
          <tei:seg xml:id="BMG_16100240_3" type="token">mit</tei:seg>
          <tei:seg xml:id="BMG_16100240_4" type="token">ougen</tei:seg>
          <tei:seg xml:id="BMG_16100240_5" type="pc">!</tei:seg>
        </tei:l>
        <tei:l n="25">
          <tei:seg xml:id="BMG_16100250_0" type="token">min</tei:seg>
          <tei:seg xml:id="BMG_16100250_1" type="token">sele</tei:seg>
          <tei:seg xml:id="BMG_16100250_2" type="token">iamert</tei:seg>
          <tei:seg xml:id="BMG_16100250_3" type="token">nah</tei:seg>
          <tei:seg xml:id="BMG_16100250_4" type="token">dir</tei:seg>
          <tei:seg xml:id="BMG_16100250_5" type="pc">.</tei:seg>
        </tei:l>
        <tei:l n="26">
          <tei:seg xml:id="BMG_16100260_0" type="token">troeste</tei:seg>
          <tei:seg xml:id="BMG_16100260_1" type="token">mich</tei:seg>
          <tei:seg xml:id="BMG_16100260_2" type="token">und</tei:seg>
          <tei:seg xml:id="BMG_16100260_3" type="token">hilf</tei:seg>
          <tei:seg xml:id="BMG_16100260_4" type="token">mir</tei:seg>
        </tei:l>
        <tei:l n="27">
          <tei:seg xml:id="BMG_16100270_0" type="token">mit</tei:seg>
          <tei:seg xml:id="BMG_16100270_1" type="token">des</tei:seg>
          <tei:seg xml:id="BMG_16100270_2" type="token">trostes</tei:seg>
          <tei:seg xml:id="BMG_16100270_3" type="token">volleist</tei:seg>
          <tei:seg xml:id="BMG_16100270_4" type="pc">!</tei:seg>
        </tei:l>
        <tei:l n="28">
          <tei:seg xml:id="BMG_16100280_0" type="token">daz</tei:seg>
          <tei:seg xml:id="BMG_16100280_1" type="token">dinen</tei:seg>
          <tei:seg xml:id="BMG_16100280_2" type="token">hailigen</tei:seg>
          <tei:seg xml:id="BMG_16100280_3" type="token">geist</tei:seg>
        </tei:l>
        <tei:l n="29">
          <tei:seg xml:id="BMG_16100290_0" type="token">nah</tei:seg>
          <tei:seg xml:id="BMG_16100290_1" type="token">diner</tei:seg>
          <tei:seg xml:id="BMG_16100290_2" type="token">urstende</tei:seg>
          <tei:seg xml:id="BMG_16100290_3" type="token">sandest</tei:seg>
        </tei:l>
        <tei:l n="30">
          <tei:seg xml:id="BMG_16100300_0" type="token">den</tei:seg>
          <tei:seg xml:id="BMG_16100300_1" type="token">iungern</tei:seg>
          <tei:seg xml:id="BMG_16100300_2" type="token">un</tei:seg>
          <tei:seg xml:id="BMG_16100300_3" type="token">in</tei:seg>
          <tei:seg xml:id="BMG_16100300_4" type="token">erwandest</tei:seg>
        </tei:l>
        <tei:l n="31">
          <tei:seg xml:id="BMG_16100310_0" type="token">ir</tei:seg>
          <tei:seg xml:id="BMG_16100310_1" type="token">unfroude</tei:seg>
          <tei:seg xml:id="BMG_16100310_2" type="token">und</tei:seg>
          <tei:seg xml:id="BMG_16100310_3" type="token">ir</tei:seg>
          <tei:seg xml:id="BMG_16100310_4" type="token">unchraft</tei:seg>
          <tei:seg xml:id="BMG_16100310_5" type="pc">,</tei:seg>
        </tei:l>
        <tei:l n="32">
          <tei:seg xml:id="BMG_16100320_0" type="token">also</tei:seg>
          <tei:seg xml:id="BMG_16100320_1" type="token">mache</tei:seg>
          <tei:seg xml:id="BMG_16100320_2" type="token">mich</tei:seg>
          <tei:seg xml:id="BMG_16100320_3" type="pc">,</tei:seg>
          <tei:seg xml:id="BMG_16100320_4" type="token">herre</tei:seg>
          <tei:seg xml:id="BMG_16100320_5" type="pc">,</tei:seg>
          <tei:seg xml:id="BMG_16100320_6" type="token">sigehaft</tei:seg>
        </tei:l>
        <tei:l n="33">
          <tei:seg xml:id="BMG_16100330_0" type="token">an</tei:seg>
          <tei:seg xml:id="BMG_16100330_1" type="token">allem</tei:seg>
          <tei:seg xml:id="BMG_16100330_2" type="token">dem</tei:seg>
          <tei:seg xml:id="BMG_16100330_3" type="pc">,</tei:seg>
          <tei:seg xml:id="BMG_16100330_4" type="token">daz</tei:seg>
          <tei:seg xml:id="BMG_16100330_5" type="token">mir</tei:seg>
          <tei:seg xml:id="BMG_16100330_6" type="token">wirret</tei:seg>
        </tei:l>
        <tei:l n="34">
          <tei:seg xml:id="BMG_16100340_0" type="token">und</tei:seg>
          <tei:seg xml:id="BMG_16100340_1" type="token">mich</tei:seg>
          <tei:seg xml:id="BMG_16100340_2" type="token">dines</tei:seg>
          <tei:seg xml:id="BMG_16100340_3" type="token">richez</tei:seg>
          <tei:seg xml:id="BMG_16100340_4" type="token">irret</tei:seg>
          <tei:seg xml:id="BMG_16100340_5" type="pc">!</tei:seg>
        </tei:l>
        <tei:l n="35">
          <tei:seg xml:id="BMG_16100350_0" type="token">schepfære</tei:seg>
          <tei:seg xml:id="BMG_16100350_1" type="token">himels</tei:seg>
          <tei:seg xml:id="BMG_16100350_2" type="token">und</tei:seg>
          <tei:supplied>
            <tei:seg xml:id="BMG_16100350_3" type="token">der</tei:seg>
          </tei:supplied>
          <tei:seg xml:id="BMG_16100350_4" type="token">erden</tei:seg>
          <tei:seg xml:id="BMG_16100350_5" type="pc">,</tei:seg>
        </tei:l>
        <tei:l n="36">
          <tei:seg xml:id="BMG_16100360_0" type="token">la</tei:seg>
          <tei:seg xml:id="BMG_16100360_1" type="token">mich</tei:seg>
          <tei:seg xml:id="BMG_16100360_2" type="pc">,</tei:seg>
          <tei:seg xml:id="BMG_16100360_3" type="token">herre</tei:seg>
          <tei:seg xml:id="BMG_16100360_4" type="pc">,</tei:seg>
          <tei:supplied>
            <tei:seg xml:id="BMG_16100360_5" type="token">uber</tei:seg>
          </tei:supplied>
          <tei:seg xml:id="BMG_16100360_6" type="token">werden</tei:seg>
        </tei:l>
        <tei:l n="37">
          <tei:seg xml:id="BMG_16100370_0" type="token">des</tei:seg>
          <tei:seg xml:id="BMG_16100370_1" type="token">ewigen</tei:seg>
          <tei:seg xml:id="BMG_16100370_2" type="token">unhailes</tei:seg>
          <tei:seg xml:id="BMG_16100370_3" type="pc">,</tei:seg>
        </tei:l>
        <tei:l n="38">
          <tei:seg xml:id="BMG_16100380_0" type="token">dines</tei:seg>
          <tei:seg xml:id="BMG_16100380_1" type="token">angestlichen</tei:seg>
          <tei:seg xml:id="BMG_16100380_2" type="token">urteiles</tei:seg>
          <tei:seg xml:id="BMG_16100380_3" type="pc">!</tei:seg>
        </tei:l>
        <tei:l n="39">
          <tei:seg xml:id="BMG_16100390_0" type="token">des</tei:seg>
          <tei:seg xml:id="BMG_16100390_1" type="token">peiten</tei:seg>
          <tei:seg xml:id="BMG_16100390_2" type="token">wir</tei:seg>
          <tei:seg xml:id="BMG_16100390_3" type="token">armen</tei:seg>
          <tei:seg xml:id="BMG_16100390_4" type="token">alle</tei:seg>
          <tei:seg xml:id="BMG_16100390_5" type="token">hie</tei:seg>
          <tei:seg xml:id="BMG_16100390_6" type="pc">.</tei:seg>
        </tei:l>
        <tei:l n="40">
          <tei:seg xml:id="BMG_16100400_0" type="token">da</tei:seg>
          <tei:seg xml:id="BMG_16100400_1" type="token">fur</tei:seg>
          <tei:seg xml:id="BMG_16100400_2" type="token">dich</tei:seg>
          <tei:seg xml:id="BMG_16100400_3" type="token">choment</tei:seg>
          <tei:seg xml:id="BMG_16100400_4" type="token">alle</tei:seg>
          <tei:seg xml:id="BMG_16100400_5" type="token">die</tei:seg>
          <tei:seg xml:id="BMG_16100400_6" type="pc">,</tei:seg>
        </tei:l>
        <tei:l n="41">
          <tei:seg xml:id="BMG_16100410_0" type="token">die</tei:seg>
          <tei:seg xml:id="BMG_16100410_1" type="token">ubel</tei:seg>
          <tei:seg xml:id="BMG_16100410_2" type="token">ode</tei:seg>
          <tei:seg xml:id="BMG_16100410_3" type="token">guot</tei:seg>
          <tei:seg xml:id="BMG_16100410_4" type="token">sint</tei:seg>
          <tei:seg xml:id="BMG_16100410_5" type="pc">,</tei:seg>
        </tei:l>
        <tei:l n="42">
          <tei:seg xml:id="BMG_16100420_0" type="token">da</tei:seg>
          <tei:seg xml:id="BMG_16100420_1" type="token">froewe</tei:seg>
          <tei:seg xml:id="BMG_16100420_2" type="token">mich</tei:seg>
          <tei:seg xml:id="BMG_16100420_3" type="pc">,</tei:seg>
          <tei:seg xml:id="BMG_16100420_4" type="token">sant</tei:seg>
          <tei:seg xml:id="BMG_16100420_5" type="token">marien</tei:seg>
          <tei:seg xml:id="BMG_16100420_6" type="token">chint</tei:seg>
          <tei:seg xml:id="BMG_16100420_7" type="pc">,</tei:seg>
        </tei:l>
        <tei:l n="43">
          <tei:seg xml:id="BMG_16100430_0" type="token">und</tei:seg>
          <tei:seg xml:id="BMG_16100430_1" type="token">la</tei:seg>
          <tei:seg xml:id="BMG_16100430_2" type="token">mich</tei:seg>
          <tei:seg xml:id="BMG_16100430_3" type="token">beliben</tei:seg>
          <tei:seg xml:id="BMG_16100430_4" type="token">bi</tei:seg>
          <tei:seg xml:id="BMG_16100430_5" type="token">dir</tei:seg>
        </tei:l>
        <tei:l n="44">
          <tei:seg xml:id="BMG_16100440_0" type="token">und</tei:seg>
          <tei:seg xml:id="BMG_16100440_1" type="token">alle</tei:seg>
          <tei:seg xml:id="BMG_16100440_2" type="token">die</tei:seg>
          <tei:seg xml:id="BMG_16100440_3" type="token">menschen</tei:seg>
          <tei:seg xml:id="BMG_16100440_4" type="token">mit</tei:seg>
          <tei:seg xml:id="BMG_16100440_5" type="token">mir</tei:seg>
          <tei:seg xml:id="BMG_16100440_6" type="pc">,</tei:seg>
        </tei:l>
        <tei:l n="45">
          <tei:seg xml:id="BMG_16100450_0" type="token">umbe</tei:seg>
          <tei:seg xml:id="BMG_16100450_1" type="token">die</tei:seg>
          <tei:seg xml:id="BMG_16100450_2" type="token">dich</tei:seg>
          <tei:seg xml:id="BMG_16100450_3" type="token">iemen</tei:seg>
          <tei:seg xml:id="BMG_16100450_4" type="token">bitten</tei:seg>
          <tei:seg xml:id="BMG_16100450_5" type="token">sol</tei:seg>
          <tei:seg xml:id="BMG_16100450_6" type="pc">!</tei:seg>
        </tei:l>
        <tei:l n="46">
          <tei:seg xml:id="BMG_16100460_0" type="token">la</tei:seg>
          <tei:seg xml:id="BMG_16100460_1" type="token">uns</tei:seg>
          <tei:seg xml:id="BMG_16100460_2" type="token">gelingen</tei:seg>
          <tei:seg xml:id="BMG_16100460_3" type="token">so</tei:seg>
          <tei:seg xml:id="BMG_16100460_4" type="token">wol</tei:seg>
          <tei:seg xml:id="BMG_16100460_5" type="pc">,</tei:seg>
        </tei:l>
        <tei:l n="47">
          <tei:seg xml:id="BMG_16100470_0" type="token">daz</tei:seg>
          <tei:seg xml:id="BMG_16100470_1" type="token">wir</tei:seg>
          <tei:seg xml:id="BMG_16100470_2" type="token">dich</tei:seg>
          <tei:seg xml:id="BMG_16100470_3" type="token">ewiclichen</tei:seg>
          <tei:seg xml:id="BMG_16100470_4" type="token">sehen</tei:seg>
          <tei:seg xml:id="BMG_16100470_5" type="pc">,</tei:seg>
        </tei:l>
        <tei:l n="48">
          <tei:seg xml:id="BMG_16100480_0" type="token">als</tei:seg>
          <tei:seg xml:id="BMG_16100480_1" type="token">uns</tei:seg>
          <tei:seg xml:id="BMG_16100480_2" type="token">din</tei:seg>
          <tei:seg xml:id="BMG_16100480_3" type="token">gehæize</tei:seg>
          <tei:seg xml:id="BMG_16100480_4" type="token">hat</tei:seg>
          <tei:seg xml:id="BMG_16100480_5" type="token">veriehen</tei:seg>
          <tei:seg xml:id="BMG_16100480_6" type="pc">!</tei:seg>
        </tei:l>
      </tei:p>
    </tei:body>
  </tei:text>
</tei:TEI>
