<?xml version="1.0" encoding="UTF-8"?>
<?xml-model href="../../schemata/tei_all.rnc" type="application/relax-ng-compact-syntax"?>
<tei:TEI xmlns:tei="http://www.tei-c.org/ns/1.0" xmlns:xsd="http://www.w3.org/2001/XMLSchema" xmlns:mhdbdb="http://www.dhplus.sbg.ac.at/mhdbdb/" xml:id="KIH">
  <tei:teiHeader>
            <tei:fileDesc>
                <tei:titleStmt>
                    <tei:title>KIH</tei:title>
                </tei:titleStmt>
                <tei:publicationStmt>
                    <tei:p>
                        Dieser Header ist ein Platzhalter zur Validierung der Datei. 
                        Der Eigentliche Header wird aus den RDF-Daten erzeugt werden.
                    </tei:p>
                </tei:publicationStmt>
                <tei:sourceDesc>
                    <tei:p>MHDBDB</tei:p>
                </tei:sourceDesc>
            </tei:fileDesc>
        </tei:teiHeader>
  <tei:text>
    <tei:body>
      <tei:p resp="Generated by Export-Script">
        <tei:l n="1">
          <tei:hi rend="initial">
            <tei:seg xml:id="KIH_90100010_0" type="token" lemmaRef="1762" meaningRef="2752" pos="PRO" wordRef="6021">ez</tei:seg>
          </tei:hi>
          <tei:seg xml:id="KIH_90100010_1" type="token" lemmaRef="7505" meaningRef="12246" pos="VRB" wordRef="32074">was</tei:seg>
          <tei:seg xml:id="KIH_90100010_2" type="token" lemmaRef="1331" meaningRef="2068" pos="ART NUM" wordRef="4319">ein</tei:seg>
          <tei:seg xml:id="KIH_90100010_3" type="token" lemmaRef="152" meaningRef="187" pos="ADV" wordRef="378">also</tei:seg>
          <tei:seg xml:id="KIH_90100010_4" type="token" lemmaRef="4872" meaningRef="7549" pos="NOM ADJ ADV" wordRef="78765">riche</tei:seg>
          <tei:seg xml:id="KIH_90100010_5" type="token" lemmaRef="3957" meaningRef="6236" pos="NOM" wordRef="13798">man</tei:seg>
          <tei:seg xml:id="KIH_90100010_6" type="pc">,</tei:seg>
        </tei:l>
        <tei:l n="2">
          <tei:seg xml:id="KIH_90100020_0" type="token" lemmaRef="1097" meaningRef="1741" pos="ART CNJ" wordRef="3398">daz</tei:seg>
          <tei:seg xml:id="KIH_90100020_1" type="token" lemmaRef="4366" meaningRef="6823" pos="ADJ PRO NEG" wordRef="15237">niemen</tei:seg>
          <tei:seg xml:id="KIH_90100020_2" type="token" lemmaRef="3028" meaningRef="4833" pos="PRP" wordRef="10369">in</tei:seg>
          <tei:seg xml:id="KIH_90100020_3" type="token" lemmaRef="1119" meaningRef="1770" pos="ART" wordRef="3507">der</tei:seg>
          <tei:seg xml:id="KIH_90100020_4" type="token" lemmaRef="7857" meaningRef="12879" pos="NOM" wordRef="28470">zit</tei:seg>
          <tei:seg xml:id="KIH_90100020_5" type="token" lemmaRef="2348" meaningRef="3773" pos="VRB" wordRef="7930">gewan</tei:seg>
        </tei:l>
        <tei:l n="3">
          <tei:seg xml:id="KIH_90100030_0" type="token" lemmaRef="5601" meaningRef="8764" pos="ADV" wordRef="19596">so</tei:seg>
          <tei:seg xml:id="KIH_90100030_1" type="token" lemmaRef="4840" meaningRef="18804" pos="NOM ADJ" wordRef="16638">rehte</tei:seg>
          <tei:seg xml:id="KIH_90100030_2" type="token" lemmaRef="2534" meaningRef="4057" pos="ADJ" wordRef="8499">grozen</tei:seg>
          <tei:seg xml:id="KIH_90100030_3" type="token" lemmaRef="21246" meaningRef="34904" pos="NOM" wordRef="116584">rihtuom</tei:seg>
          <tei:seg xml:id="KIH_90100030_4" type="pc">.</tei:seg>
        </tei:l>
        <tei:l n="4">
          <tei:seg xml:id="KIH_90100040_0" type="token" lemmaRef="1258" meaningRef="1977" pos="PRP" wordRef="4044">durch</tei:seg>
          <tei:seg xml:id="KIH_90100040_1" type="token" lemmaRef="1517" meaningRef="2355" pos="POS" wordRef="5023">sinen</tei:seg>
          <tei:seg xml:id="KIH_90100040_2" type="token" lemmaRef="6282" meaningRef="9903" pos="ADJ ADV" wordRef="22219">tugentlichen</tei:seg>
          <tei:seg xml:id="KIH_90100040_3" type="token" lemmaRef="5030" meaningRef="7812" pos="NOM" wordRef="17418">ruom</tei:seg>
        </tei:l>
        <tei:l n="5">
          <tei:seg xml:id="KIH_90100050_0" type="token" lemmaRef="4649" meaningRef="7214" pos="VRB" wordRef="16006">pflac</tei:seg>
          <tei:seg xml:id="KIH_90100050_1" type="token" lemmaRef="1517" meaningRef="2355" pos="PRO" wordRef="4999">er</tei:seg>
          <tei:seg xml:id="KIH_90100050_2" type="token" lemmaRef="2534" meaningRef="4057" pos="ADJ" wordRef="8500">grozer</tei:seg>
          <tei:seg xml:id="KIH_90100050_3" type="token" lemmaRef="2687" meaningRef="4326" pos="NOM" wordRef="9048">herschaft</tei:seg>
          <tei:seg xml:id="KIH_90100050_4" type="pc">.</tei:seg>
        </tei:l>
        <tei:l n="6">
          <tei:seg xml:id="KIH_90100060_0" type="token" lemmaRef="1517" meaningRef="2355" pos="PRO" wordRef="4999">er</tei:seg>
          <tei:seg xml:id="KIH_90100060_1" type="token" lemmaRef="2598" meaningRef="4170" pos="VRB VEX" wordRef="8767">het</tei:seg>
          <tei:seg xml:id="KIH_90100060_2" type="token" lemmaRef="2573" meaningRef="4120" pos="NOM ADJ" wordRef="42821">gutes</tei:seg>
          <tei:seg xml:id="KIH_90100060_3" type="token" lemmaRef="1139" meaningRef="1797" pos="ART" wordRef="3568">die</tei:seg>
          <tei:seg xml:id="KIH_90100060_4" type="token" lemmaRef="3437" meaningRef="5414" pos="NOM" wordRef="42148">chraft</tei:seg>
          <tei:seg xml:id="KIH_90100060_5" type="pc">,</tei:seg>
        </tei:l>
        <tei:l n="7">
          <tei:seg xml:id="KIH_90100070_0" type="token" lemmaRef="1097" meaningRef="1741" pos="ART CNJ" wordRef="3398">daz</tei:seg>
          <tei:seg xml:id="KIH_90100070_1" type="token" lemmaRef="1517" meaningRef="2355" pos="PRO" wordRef="4999">er</tei:seg>
          <tei:seg xml:id="KIH_90100070_2" type="token" lemmaRef="4377" meaningRef="6838" pos="NOM ADJ ADV NEG" wordRef="15288">nihtes</tei:seg>
          <tei:seg xml:id="KIH_90100070_3" type="token" lemmaRef="30771" meaningRef="48193" pos="NEG VRB" wordRef="158325">enbar</tei:seg>
          <tei:seg xml:id="KIH_90100070_4" type="pc">.</tei:seg>
        </tei:l>
        <tei:l n="8">
          <tei:seg xml:id="KIH_90100080_0" type="token" lemmaRef="1517" meaningRef="2355" pos="PRO" wordRef="4999">er</tei:seg>
          <tei:seg xml:id="KIH_90100080_1" type="token" lemmaRef="7473" meaningRef="12160" pos="VRB VEM" wordRef="26936">wolt</tei:seg>
          <tei:seg xml:id="KIH_90100080_2" type="token" lemmaRef="1762" meaningRef="2752" pos="PRO" wordRef="6021">ez</tei:seg>
          <tei:seg xml:id="KIH_90100080_3" type="token" lemmaRef="106" meaningRef="139" pos="ADJ ADV" wordRef="264">allez</tei:seg>
          <tei:seg xml:id="KIH_90100080_4" type="token" lemmaRef="2598" meaningRef="4170" pos="VRB VEX" wordRef="8731">haben</tei:seg>
          <tei:seg xml:id="KIH_90100080_5" type="token" lemmaRef="1913" meaningRef="2938" pos="ADJ ADV" wordRef="6476">gar</tei:seg>
          <tei:seg xml:id="KIH_90100080_6" type="pc">,</tei:seg>
        </tei:l>
        <tei:l n="9">
          <tei:seg xml:id="KIH_90100090_0" type="token" lemmaRef="5961" meaningRef="9448" pos="PRO IPA" wordRef="21018">swes</tei:seg>
          <tei:seg xml:id="KIH_90100090_1" type="token" lemmaRef="1517" meaningRef="2355" pos="PRO" wordRef="5008">in</tei:seg>
          <tei:seg xml:id="KIH_90100090_2" type="token" lemmaRef="5385" meaningRef="8406" pos="ADJ" wordRef="18766">selbe</tei:seg>
          <tei:seg xml:id="KIH_90100090_3" type="token" lemmaRef="2362" meaningRef="3807" pos="VRB" wordRef="7993">gezam</tei:seg>
        </tei:l>
        <tei:l n="10">
          <tei:seg xml:id="KIH_90100100_0" type="token" lemmaRef="6467" meaningRef="10233" pos="CNJ" wordRef="22825">und</tei:seg>
          <tei:seg xml:id="KIH_90100100_1" type="token" lemmaRef="1517" meaningRef="2355" pos="POS" wordRef="5023">sinen</tei:seg>
          <tei:seg xml:id="KIH_90100100_2" type="token" lemmaRef="1282" meaningRef="2011" pos="NOM" wordRef="42751">eren</tei:seg>
          <tei:seg xml:id="KIH_90100100_3" type="token" lemmaRef="4840" meaningRef="18804" pos="NOM ADJ" wordRef="16638">rehte</tei:seg>
          <tei:seg xml:id="KIH_90100100_4" type="token" lemmaRef="3400" meaningRef="5361" pos="VRB" wordRef="11734">quam</tei:seg>
          <tei:seg xml:id="KIH_90100100_5" type="pc">.</tei:seg>
        </tei:l>
        <tei:l n="11">
          <tei:seg xml:id="KIH_90100110_0" type="token" lemmaRef="1517" meaningRef="2355" pos="PRO" wordRef="4999">er</tei:seg>
          <tei:seg xml:id="KIH_90100110_1" type="token" lemmaRef="2598" meaningRef="4170" pos="VRB VEX" wordRef="8767">het</tei:seg>
          <tei:seg xml:id="KIH_90100110_2" type="token" lemmaRef="1331" meaningRef="2068" pos="ART NUM" wordRef="4322">einen</tei:seg>
          <tei:seg xml:id="KIH_90100110_3" type="token" lemmaRef="1327" meaningRef="2061" pos="NOM ADJ" wordRef="4306">eigen</tei:seg>
          <tei:seg xml:id="KIH_90100110_4" type="token" lemmaRef="3377" meaningRef="5319" pos="NOM" wordRef="46464">chneht</tei:seg>
          <tei:seg xml:id="KIH_90100110_5" type="pc">;</tei:seg>
        </tei:l>
        <tei:l n="12">
          <tei:seg xml:id="KIH_90100120_0" type="token" lemmaRef="1119" meaningRef="1770" pos="ART" wordRef="3507">der</tei:seg>
          <tei:seg xml:id="KIH_90100120_1" type="token" lemmaRef="5608" meaningRef="8771" pos="VRB VEM" wordRef="19653">solde</tei:seg>
          <tei:seg xml:id="KIH_90100120_2" type="token" lemmaRef="1517" meaningRef="2355" pos="PRO" wordRef="32780">im</tei:seg>
          <tei:seg xml:id="KIH_90100120_3" type="token" lemmaRef="1145" meaningRef="1804" pos="VRB" wordRef="3591">dienen</tei:seg>
          <tei:seg xml:id="KIH_90100120_4" type="pc">,</tei:seg>
          <tei:seg xml:id="KIH_90100120_5" type="token" lemmaRef="1097" meaningRef="1741" pos="ART CNJ" wordRef="3398">daz</tei:seg>
          <tei:seg xml:id="KIH_90100120_6" type="token" lemmaRef="7505" meaningRef="12246" pos="VRB" wordRef="32074">was</tei:seg>
          <tei:seg xml:id="KIH_90100120_7" type="token" lemmaRef="4840" meaningRef="7495" pos="NOM ADJ ADV" wordRef="16637">reht</tei:seg>
          <tei:seg xml:id="KIH_90100120_8" type="pc">.</tei:seg>
        </tei:l>
        <tei:l n="13">
          <tei:seg xml:id="KIH_90100130_0" type="token" lemmaRef="1119" meaningRef="1770" pos="ART" wordRef="3504">dem</tei:seg>
          <tei:seg xml:id="KIH_90100130_1" type="token" lemmaRef="2731" meaningRef="4403" pos="VRB" wordRef="9214">hiez</tei:seg>
          <tei:seg xml:id="KIH_90100130_2" type="token" lemmaRef="1517" meaningRef="2355" pos="PRO" wordRef="4999">er</tei:seg>
          <tei:seg xml:id="KIH_90100130_3" type="token" lemmaRef="3352" meaningRef="5266" pos="NOM" wordRef="46511">chleider</tei:seg>
          <tei:seg xml:id="KIH_90100130_4" type="token" lemmaRef="3917" meaningRef="6181" pos="VRB" wordRef="13685">machen</tei:seg>
          <tei:seg xml:id="KIH_90100130_5" type="pc">,</tei:seg>
        </tei:l>
        <tei:l n="14">
          <tei:seg xml:id="KIH_90100140_0" type="token" lemmaRef="1097" meaningRef="1741" pos="ART CNJ" wordRef="3398">daz</tei:seg>
          <tei:seg xml:id="KIH_90100140_1" type="token" lemmaRef="7193" meaningRef="11656" pos="PRP" wordRef="25544">von</tei:seg>
          <tei:seg xml:id="KIH_90100140_2" type="token" lemmaRef="5601" meaningRef="8764" pos="ADV" wordRef="19596">so</tei:seg>
          <tei:seg xml:id="KIH_90100140_3" type="token" lemmaRef="4872" meaningRef="7550" pos="NOM ADJ" wordRef="16765">richen</tei:seg>
          <tei:seg xml:id="KIH_90100140_4" type="token" lemmaRef="5046" meaningRef="43573" pos="NOM" wordRef="17464">sachen</tei:seg>
        </tei:l>
        <tei:l n="15">
          <tei:seg xml:id="KIH_90100150_0" type="token" lemmaRef="4365" meaningRef="6822" pos="ADV NEG" wordRef="15230">nie</tei:seg>
          <tei:seg xml:id="KIH_90100150_1" type="token" lemmaRef="3377" meaningRef="5319" pos="NOM" wordRef="46464">chneht</tei:seg>
          <tei:seg xml:id="KIH_90100150_2" type="token" lemmaRef="3352" meaningRef="5266" pos="NOM" wordRef="46511">chleider</tei:seg>
          <tei:seg xml:id="KIH_90100150_3" type="token" lemmaRef="6171" meaningRef="9727" pos="VRB" wordRef="21750">getruoc</tei:seg>
          <tei:seg xml:id="KIH_90100150_4" type="pc">.</tei:seg>
        </tei:l>
        <tei:l n="16">
          <tei:seg xml:id="KIH_90100160_0" type="token" lemmaRef="1139" meaningRef="1797" pos="ART" wordRef="45021">diu</tei:seg>
          <tei:seg xml:id="KIH_90100160_1" type="token" lemmaRef="2731" meaningRef="4403" pos="VRB" wordRef="9214">hiez</tei:seg>
          <tei:seg xml:id="KIH_90100160_2" type="token" lemmaRef="1517" meaningRef="2355" pos="PRO" wordRef="4999">er</tei:seg>
          <tei:seg xml:id="KIH_90100160_3" type="token" lemmaRef="7864" meaningRef="12897" pos="VRB" wordRef="28546">zieren</tei:seg>
          <tei:seg xml:id="KIH_90100160_4" type="token" lemmaRef="2141" meaningRef="3333" pos="ADJ ADV" wordRef="7272">genuoc</tei:seg>
        </tei:l>
        <tei:l n="17">
          <tei:seg xml:id="KIH_90100170_0" type="token" lemmaRef="4172" meaningRef="6544" pos="PRP" wordRef="14531">mit</tei:seg>
          <tei:seg xml:id="KIH_90100170_1" type="token" lemmaRef="2453" meaningRef="3939" pos="NOM" wordRef="8222">golde</tei:seg>
          <tei:seg xml:id="KIH_90100170_2" type="token" lemmaRef="6467" meaningRef="10233" pos="CNJ" wordRef="22825">und</tei:seg>
          <tei:seg xml:id="KIH_90100170_3" type="token" lemmaRef="4172" meaningRef="6544" pos="PRP" wordRef="14531">mit</tei:seg>
          <tei:seg xml:id="KIH_90100170_4" type="token" lemmaRef="2250" meaningRef="3583" pos="NOM" wordRef="7608">gesteine</tei:seg>
          <tei:seg xml:id="KIH_90100170_5" type="pc">:</tei:seg>
        </tei:l>
        <tei:l n="18">
          <tei:seg xml:id="KIH_90100180_0" type="token" lemmaRef="106" meaningRef="139" pos="ADJ ADV" wordRef="264">allez</tei:seg>
          <tei:seg xml:id="KIH_90100180_1" type="token" lemmaRef="1097" meaningRef="1741" pos="ART CNJ" wordRef="3398">daz</tei:seg>
          <tei:seg xml:id="KIH_90100180_2" type="token" lemmaRef="2097" meaningRef="3246" pos="NOM ADJ ADV" wordRef="7083">gemeine</tei:seg>
          <tei:seg xml:id="KIH_90100180_3" type="pc">,</tei:seg>
        </tei:l>
        <tei:l n="19">
          <tei:seg xml:id="KIH_90100190_0" type="token" lemmaRef="1055" meaningRef="1689" pos="ADV CNJ" wordRef="3255">da</tei:seg>
          <tei:seg xml:id="KIH_90100190_1" type="token" lemmaRef="4172" meaningRef="6544" pos="PRP" wordRef="14531">mit</tei:seg>
          <tei:seg xml:id="KIH_90100190_2" type="token" lemmaRef="3958" meaningRef="6240" pos="PRO" wordRef="13805">man</tei:seg>
          <tei:seg xml:id="KIH_90100190_3" type="token" lemmaRef="7864" meaningRef="12897" pos="VRB" wordRef="28546">zieren</tei:seg>
          <tei:seg xml:id="KIH_90100190_4" type="token" lemmaRef="5608" meaningRef="8771" pos="VRB VEM" wordRef="19653">solde</tei:seg>
          <tei:seg xml:id="KIH_90100190_5" type="pc">,</tei:seg>
        </tei:l>
        <tei:l n="20">
          <tei:seg xml:id="KIH_90100200_0" type="token" lemmaRef="5941" meaningRef="9416" pos="PRO IPA" wordRef="20940">swaz</tei:seg>
          <tei:seg xml:id="KIH_90100200_1" type="token" lemmaRef="3958" meaningRef="6240" pos="PRO" wordRef="13805">man</tei:seg>
          <tei:seg xml:id="KIH_90100200_2" type="token" lemmaRef="7864" meaningRef="12898" pos="VRB" wordRef="28546">zieren</tei:seg>
          <tei:seg xml:id="KIH_90100200_3" type="token" lemmaRef="7473" meaningRef="12160" pos="VRB VEM" wordRef="26927">wolde</tei:seg>
          <tei:seg xml:id="KIH_90100200_4" type="pc">.</tei:seg>
        </tei:l>
        <tei:l n="21">
          <tei:seg xml:id="KIH_90100210_0" type="token" lemmaRef="1119" meaningRef="1770" pos="ART" wordRef="3510">des</tei:seg>
          <tei:seg xml:id="KIH_90100210_1" type="token" lemmaRef="7489" meaningRef="12208" pos="VRB VEX" wordRef="49215">wart</tei:seg>
          <tei:seg xml:id="KIH_90100210_2" type="token" lemmaRef="7722" meaningRef="12653" pos="NOM" wordRef="27977">wunders</tei:seg>
          <tei:seg xml:id="KIH_90100210_3" type="token" lemmaRef="8028" meaningRef="13094" pos="ADV" wordRef="28996">daran</tei:seg>
          <tei:seg xml:id="KIH_90100210_4" type="token" lemmaRef="3674" meaningRef="5808" pos="VRB" wordRef="12767">geleit</tei:seg>
          <tei:seg xml:id="KIH_90100210_5" type="pc">.</tei:seg>
        </tei:l>
        <tei:l n="22">
          <tei:seg xml:id="KIH_90100220_0" type="token" lemmaRef="4172" meaningRef="6544" pos="PRP" wordRef="14531">mit</tei:seg>
          <tei:seg xml:id="KIH_90100220_1" type="token" lemmaRef="152" meaningRef="187" pos="ADV" wordRef="378">also</tei:seg>
          <tei:seg xml:id="KIH_90100220_2" type="token" lemmaRef="4872" meaningRef="7549" pos="ADJ GRA" wordRef="16766">richer</tei:seg>
          <tei:seg xml:id="KIH_90100220_3" type="token" lemmaRef="5283" meaningRef="8237" pos="NOM" wordRef="35306">schonheit</tei:seg>
        </tei:l>
        <tei:l n="23">
          <tei:seg xml:id="KIH_90100230_0" type="token" lemmaRef="527" meaningRef="21930" pos="VRB" wordRef="59991">bereitte</tei:seg>
          <tei:seg xml:id="KIH_90100230_1" type="token" lemmaRef="3958" meaningRef="6240" pos="PRO" wordRef="13805">man</tei:seg>
          <tei:seg xml:id="KIH_90100230_2" type="token" lemmaRef="1139" meaningRef="1797" pos="ART" wordRef="3568">die</tei:seg>
          <tei:seg xml:id="KIH_90100230_3" type="token" lemmaRef="3352" meaningRef="5266" pos="NOM" wordRef="46511">chleider</tei:seg>
          <tei:seg xml:id="KIH_90100230_4" type="token" lemmaRef="1913" meaningRef="2938" pos="ADJ ADV" wordRef="6476">gar</tei:seg>
        </tei:l>
        <tei:l n="24">
          <tei:seg xml:id="KIH_90100240_0" type="token" lemmaRef="6467" meaningRef="10233" pos="CNJ" wordRef="22825">und</tei:seg>
          <tei:seg xml:id="KIH_90100240_1" type="token" lemmaRef="1961" meaningRef="3008" pos="VRB" wordRef="6611">gab</tei:seg>
          <tei:seg xml:id="KIH_90100240_2" type="token" lemmaRef="5454" meaningRef="8506" pos="POS PRO" wordRef="19043">si</tei:seg>
          <tei:seg xml:id="KIH_90100240_3" type="token" lemmaRef="1119" meaningRef="1770" pos="ART" wordRef="3504">dem</tei:seg>
          <tei:seg xml:id="KIH_90100240_4" type="token" lemmaRef="3377" meaningRef="5319" pos="NOM" wordRef="41769">chnehte</tei:seg>
          <tei:seg xml:id="KIH_90100240_5" type="token" lemmaRef="1055" meaningRef="1689" pos="ADV" wordRef="3258">dar</tei:seg>
          <tei:seg xml:id="KIH_90100240_6" type="pc">.</tei:seg>
        </tei:l>
        <tei:l n="25">
          <tei:seg xml:id="KIH_90100250_0" type="token" lemmaRef="148" meaningRef="183" pos="CNJ" wordRef="369">als</tei:seg>
          <tei:seg xml:id="KIH_90100250_1" type="token" lemmaRef="1517" meaningRef="2355" pos="PRO" wordRef="4999">er</tei:seg>
          <tei:seg xml:id="KIH_90100250_2" type="token" lemmaRef="1139" meaningRef="1797" pos="ART" wordRef="3568">die</tei:seg>
          <tei:seg xml:id="KIH_90100250_3" type="token" lemmaRef="3352" meaningRef="5266" pos="NOM" wordRef="46511">chleider</tei:seg>
          <tei:seg xml:id="KIH_90100250_4" type="token" lemmaRef="2348" meaningRef="3773" pos="VRB" wordRef="7943">gwan</tei:seg>
          <tei:seg xml:id="KIH_90100250_5" type="pc">,</tei:seg>
        </tei:l>
        <tei:l n="26">
          <tei:seg xml:id="KIH_90100260_0" type="token" lemmaRef="1180" meaningRef="1864" pos="ADV" wordRef="3738">do</tei:seg>
          <tei:seg xml:id="KIH_90100260_1" type="token" lemmaRef="6301" meaningRef="9929" pos="NOM VRB" wordRef="22319">tet</tei:seg>
          <tei:seg xml:id="KIH_90100260_2" type="token" lemmaRef="1517" meaningRef="2355" pos="PRO" wordRef="4999">er</tei:seg>
          <tei:seg xml:id="KIH_90100260_3" type="token" lemmaRef="148" meaningRef="183" pos="CNJ" wordRef="369">als</tei:seg>
          <tei:seg xml:id="KIH_90100260_4" type="token" lemmaRef="1331" meaningRef="2068" pos="ART NUM" wordRef="4319">ein</tei:seg>
          <tei:seg xml:id="KIH_90100260_5" type="token" lemmaRef="6293" meaningRef="9916" pos="ADJ GRA" wordRef="22249">tumber</tei:seg>
          <tei:seg xml:id="KIH_90100260_6" type="token" lemmaRef="3957" meaningRef="6236" pos="NOM" wordRef="13798">man</tei:seg>
          <tei:seg xml:id="KIH_90100260_7" type="pc">:</tei:seg>
        </tei:l>
        <tei:l n="27">
          <tei:seg xml:id="KIH_90100270_0" type="token" lemmaRef="1517" meaningRef="2355" pos="PRO" wordRef="4999">er</tei:seg>
          <tei:seg xml:id="KIH_90100270_1" type="token" lemmaRef="7489" meaningRef="16763" pos="VRB VEX" wordRef="49215">wart</tei:seg>
          <tei:seg xml:id="KIH_90100270_2" type="token" lemmaRef="1055" meaningRef="1689" pos="ADV CNJ" wordRef="3255">da</tei:seg>
          <tei:seg xml:id="KIH_90100270_3" type="token" lemmaRef="7193" meaningRef="11656" pos="PRP" wordRef="25544">von</tei:seg>
          <tei:seg xml:id="KIH_90100270_4" type="token" lemmaRef="5601" meaningRef="8764" pos="ADV" wordRef="19596">so</tei:seg>
          <tei:seg xml:id="KIH_90100270_5" type="token" lemmaRef="5788" meaningRef="9133" pos="NOM ADJ ADV" wordRef="20371">stolz</tei:seg>
          <tei:seg xml:id="KIH_90100270_6" type="pc">,</tei:seg>
        </tei:l>
        <tei:l n="28">
          <tei:seg xml:id="KIH_90100280_0" type="token" lemmaRef="1097" meaningRef="1741" pos="ART CNJ" wordRef="3398">daz</tei:seg>
          <tei:seg xml:id="KIH_90100280_1" type="token" lemmaRef="1517" meaningRef="2355" pos="PRO" wordRef="4999">er</tei:seg>
          <tei:seg xml:id="KIH_90100280_2" type="token" lemmaRef="33172" meaningRef="51784" pos="NOM PRP" wordRef="172527">zeacker</tei:seg>
          <tei:seg xml:id="KIH_90100280_3" type="token" lemmaRef="4415" meaningRef="64155" pos="ADV NEG CNJ" wordRef="15400">noch</tei:seg>
          <tei:seg xml:id="KIH_90100280_4" type="token" lemmaRef="13276" meaningRef="21164" pos="NOM PRP" wordRef="52046">zeholz</tei:seg>
        </tei:l>
        <tei:l n="29">
          <tei:seg xml:id="KIH_90100290_0" type="token" lemmaRef="4377" meaningRef="6838" pos="ADJ ADV NEG" wordRef="15286">niht</tei:seg>
          <tei:seg xml:id="KIH_90100290_1" type="token" lemmaRef="4034" meaningRef="6338" pos="ADJ ADV GRA" wordRef="14082">mer</tei:seg>
          <tei:seg xml:id="KIH_90100290_2" type="token" lemmaRef="6761" meaningRef="18808" pos="VRB" wordRef="23650">varn</tei:seg>
          <tei:seg xml:id="KIH_90100290_3" type="token" lemmaRef="7473" meaningRef="12160" pos="VRB VEM" wordRef="26927">wolde</tei:seg>
          <tei:seg xml:id="KIH_90100290_4" type="pc">,</tei:seg>
        </tei:l>
        <tei:l n="30">
          <tei:seg xml:id="KIH_90100300_0" type="token" lemmaRef="148" meaningRef="183" pos="CNJ" wordRef="369">als</tei:seg>
          <tei:seg xml:id="KIH_90100300_1" type="token" lemmaRef="1517" meaningRef="2355" pos="PRO" wordRef="4999">er</tei:seg>
          <tei:seg xml:id="KIH_90100300_2" type="token" lemmaRef="7193" meaningRef="11656" pos="PRP" wordRef="25544">von</tei:seg>
          <tei:seg xml:id="KIH_90100300_3" type="token" lemmaRef="4840" meaningRef="7495" pos="NOM ADJ" wordRef="16638">rehte</tei:seg>
          <tei:seg xml:id="KIH_90100300_4" type="token" lemmaRef="5608" meaningRef="8771" pos="VRB VEM" wordRef="19653">solde</tei:seg>
          <tei:seg xml:id="KIH_90100300_5" type="pc">.</tei:seg>
        </tei:l>
        <tei:l n="31">
          <tei:seg xml:id="KIH_90100310_0" type="token" lemmaRef="468" meaningRef="655" pos="ADJ" wordRef="1340">beidiu</tei:seg>
          <tei:seg xml:id="KIH_90100310_1" type="token" lemmaRef="4303" meaningRef="6730" pos="NOM" wordRef="14981">naht</tei:seg>
          <tei:seg xml:id="KIH_90100310_2" type="token" lemmaRef="6467" meaningRef="10233" pos="CNJ" wordRef="22825">und</tei:seg>
          <tei:seg xml:id="KIH_90100310_3" type="token" lemmaRef="5994" meaningRef="9496" pos="NOM" wordRef="21150">tac</tei:seg>
        </tei:l>
        <tei:l n="32">
          <tei:seg xml:id="KIH_90100320_0" type="token" lemmaRef="4389" meaningRef="6850" pos="ADV CNJ" wordRef="15325">niwan</tei:seg>
          <tei:seg xml:id="KIH_90100320_1" type="token" lemmaRef="2879" meaningRef="4618" pos="NOM ADJ" wordRef="172528">hofschens</tei:seg>
          <tei:seg xml:id="KIH_90100320_2" type="token" lemmaRef="1517" meaningRef="2355" pos="PRO" wordRef="4999">er</tei:seg>
          <tei:seg xml:id="KIH_90100320_3" type="token" lemmaRef="4649" meaningRef="17093" pos="VRB" wordRef="16020">phlac</tei:seg>
          <tei:seg xml:id="KIH_90100320_4" type="pc">.</tei:seg>
        </tei:l>
        <tei:l n="33">
          <tei:seg xml:id="KIH_90100330_0" type="token" lemmaRef="1180" meaningRef="1864" pos="ADV" wordRef="3738">do</tei:seg>
          <tei:seg xml:id="KIH_90100330_1" type="token" lemmaRef="1097" meaningRef="1741" pos="ART CNJ" wordRef="3398">daz</tei:seg>
          <tei:seg xml:id="KIH_90100330_2" type="token" lemmaRef="1119" meaningRef="1770" pos="ART" wordRef="3507">der</tei:seg>
          <tei:seg xml:id="KIH_90100330_3" type="token" lemmaRef="2684" meaningRef="4322" pos="NOM" wordRef="9039">herre</tei:seg>
          <tei:seg xml:id="KIH_90100330_4" type="token" lemmaRef="1645" meaningRef="2567" pos="VRB" wordRef="5586">ersach</tei:seg>
          <tei:seg xml:id="KIH_90100330_5" type="pc">,</tei:seg>
        </tei:l>
        <tei:l n="34">
          <tei:seg xml:id="KIH_90100340_0" type="token" lemmaRef="1180" meaningRef="1864" pos="ADV" wordRef="3738">do</tei:seg>
          <tei:seg xml:id="KIH_90100340_1" type="token" lemmaRef="7914" meaningRef="12977" pos="VRB" wordRef="28768">zurnt</tei:seg>
          <tei:seg xml:id="KIH_90100340_2" type="token" lemmaRef="1517" meaningRef="2355" pos="PRO" wordRef="4999">er</tei:seg>
          <tei:seg xml:id="KIH_90100340_3" type="token" lemmaRef="5351" meaningRef="8362" pos="ADV" wordRef="18618">sere</tei:seg>
          <tei:seg xml:id="KIH_90100340_4" type="token" lemmaRef="6467" meaningRef="10233" pos="CNJ" wordRef="22825">und</tei:seg>
          <tei:seg xml:id="KIH_90100340_5" type="token" lemmaRef="5693" meaningRef="8912" pos="VRB" wordRef="19957">sprach</tei:seg>
          <tei:seg xml:id="KIH_90100340_6" type="pc">:</tei:seg>
        </tei:l>
        <tei:l n="35">
          <tei:seg xml:id="KIH_90100350_0" type="pc">&lt;</tei:seg>
          <tei:seg xml:id="KIH_90100350_1" type="token" lemmaRef="5434" meaningRef="8481" pos="ADV PRP CNJ" wordRef="79335">sit</tei:seg>
          <tei:seg xml:id="KIH_90100350_2" type="token" lemmaRef="3001" meaningRef="4805" pos="PRO" wordRef="10212">ich</tei:seg>
          <tei:seg xml:id="KIH_90100350_3" type="token" lemmaRef="1119" meaningRef="1770" pos="ART" wordRef="3510">des</tei:seg>
          <tei:seg xml:id="KIH_90100350_4" type="token" lemmaRef="1419" meaningRef="2187" pos="VRB" wordRef="4630">engelten</tei:seg>
          <tei:seg xml:id="KIH_90100350_5" type="token" lemmaRef="5608" meaningRef="14919" pos="VRB VEM" wordRef="19651">sol</tei:seg>
          <tei:seg xml:id="KIH_90100350_6" type="pc">,</tei:seg>
        </tei:l>
        <tei:l n="36">
          <tei:seg xml:id="KIH_90100360_0" type="token" lemmaRef="1097" meaningRef="1741" pos="ART CNJ" wordRef="3398">daz</tei:seg>
          <tei:seg xml:id="KIH_90100360_1" type="token" lemmaRef="3001" meaningRef="4805" pos="PRO" wordRef="10212">ich</tei:seg>
          <tei:seg xml:id="KIH_90100360_2" type="token" lemmaRef="1242" meaningRef="1958" pos="PRO" wordRef="3956">dich</tei:seg>
          <tei:seg xml:id="KIH_90100360_3" type="token" lemmaRef="2637" meaningRef="4242" pos="VRB" wordRef="8887">gehandelt</tei:seg>
          <tei:seg xml:id="KIH_90100360_4" type="token" lemmaRef="2598" meaningRef="77622" pos="VRB VEX" wordRef="8755">han</tei:seg>
          <tei:seg xml:id="KIH_90100360_5" type="token" lemmaRef="17656" meaningRef="30055" pos="NOM PRP" wordRef="76307">zewol</tei:seg>
          <tei:seg xml:id="KIH_90100360_6" type="pc">,</tei:seg>
        </tei:l>
        <tei:l n="37">
          <tei:seg xml:id="KIH_90100370_0" type="token" lemmaRef="1242" meaningRef="1958" pos="PRO" wordRef="3966">du</tei:seg>
          <tei:seg xml:id="KIH_90100370_1" type="token" lemmaRef="295" meaningRef="383" pos="VRB" wordRef="90790">arnest</tei:seg>
          <tei:seg xml:id="KIH_90100370_2" type="token" lemmaRef="1762" meaningRef="2752" pos="PRO" wordRef="6021">ez</tei:seg>
          <tei:seg xml:id="KIH_90100370_3" type="token" lemmaRef="7852" meaningRef="12871" pos="ADV" wordRef="49238">zeware</tei:seg>
          <tei:seg xml:id="KIH_90100370_4" type="pc">.</tei:seg>
          <tei:seg xml:id="KIH_90100370_5" type="pc">&gt;</tei:seg>
        </tei:l>
        <tei:l n="38">
          <tei:seg xml:id="KIH_90100380_0" type="token" lemmaRef="1517" meaningRef="2355" pos="PRO" wordRef="4999">er</tei:seg>
          <tei:seg xml:id="KIH_90100380_1" type="token" lemmaRef="4330" meaningRef="17202" pos="VRB" wordRef="15078">nam</tei:seg>
          <tei:seg xml:id="KIH_90100380_2" type="token" lemmaRef="1517" meaningRef="2355" pos="PRO" wordRef="5008">in</tei:seg>
          <tei:seg xml:id="KIH_90100380_3" type="token" lemmaRef="678" meaningRef="1096" pos="PRP" wordRef="2055">bi</tei:seg>
          <tei:seg xml:id="KIH_90100380_4" type="token" lemmaRef="1119" meaningRef="1770" pos="ART" wordRef="3504">dem</tei:seg>
          <tei:seg xml:id="KIH_90100380_5" type="token" lemmaRef="2590" meaningRef="4151" pos="NOM" wordRef="8692">hare</tei:seg>
        </tei:l>
        <tei:l n="39">
          <tei:seg xml:id="KIH_90100390_0" type="token" lemmaRef="6467" meaningRef="10233" pos="CNJ" wordRef="22825">und</tei:seg>
          <tei:seg xml:id="KIH_90100390_1" type="token" lemmaRef="7861" meaningRef="12885" pos="VRB" wordRef="28510">zoch</tei:seg>
          <tei:seg xml:id="KIH_90100390_2" type="token" lemmaRef="1517" meaningRef="2355" pos="PRO" wordRef="32780">im</tei:seg>
          <tei:seg xml:id="KIH_90100390_3" type="token" lemmaRef="29" meaningRef="39" pos="ADV PRP" wordRef="87">abe</tei:seg>
          <tei:seg xml:id="KIH_90100390_4" type="token" lemmaRef="1517" meaningRef="2355" pos="POS PRO" wordRef="67997">sin</tei:seg>
          <tei:seg xml:id="KIH_90100390_5" type="token" lemmaRef="2331" meaningRef="3733" pos="NOM" wordRef="7881">gewant</tei:seg>
        </tei:l>
        <tei:l n="40">
          <tei:seg xml:id="KIH_90100400_0" type="token" lemmaRef="6467" meaningRef="10233" pos="CNJ" wordRef="22825">und</tei:seg>
          <tei:seg xml:id="KIH_90100400_1" type="token" lemmaRef="2731" meaningRef="4403" pos="VRB" wordRef="9214">hiez</tei:seg>
          <tei:seg xml:id="KIH_90100400_2" type="token" lemmaRef="1517" meaningRef="2355" pos="PRO" wordRef="5008">in</tei:seg>
          <tei:seg xml:id="KIH_90100400_3" type="token" lemmaRef="7490" meaningRef="23736" pos="VRB" wordRef="27079">werfen</tei:seg>
          <tei:seg xml:id="KIH_90100400_4" type="token" lemmaRef="7778" meaningRef="12747" pos="ADV PRP" wordRef="28146">zehant</tei:seg>
        </tei:l>
        <tei:l n="41">
          <tei:seg xml:id="KIH_90100410_0" type="token" lemmaRef="3028" meaningRef="4834" pos="PRP" wordRef="10369">in</tei:seg>
          <tei:seg xml:id="KIH_90100410_1" type="token" lemmaRef="1517" meaningRef="2355" pos="POS" wordRef="5023">sinen</tei:seg>
          <tei:seg xml:id="KIH_90100410_2" type="token" lemmaRef="3241" meaningRef="5104" pos="NOM" wordRef="104807">charchære</tei:seg>
          <tei:seg xml:id="KIH_90100410_3" type="pc">.</tei:seg>
        </tei:l>
        <tei:l n="42">
          <tei:seg xml:id="KIH_90100420_0" type="token" lemmaRef="1055" meaningRef="1689" pos="ADV CNJ" wordRef="3255">da</tei:seg>
          <tei:seg xml:id="KIH_90100420_1" type="token" lemmaRef="3770" meaningRef="5960" pos="VRB" wordRef="13149">lac</tei:seg>
          <tei:seg xml:id="KIH_90100420_2" type="token" lemmaRef="1119" meaningRef="1770" pos="ART" wordRef="3507">der</tei:seg>
          <tei:seg xml:id="KIH_90100420_3" type="token" lemmaRef="2879" meaningRef="4618" pos="NOM ADJ GRA" wordRef="172529">hofschære</tei:seg>
        </tei:l>
        <tei:l n="43">
          <tei:seg xml:id="KIH_90100430_0" type="token" lemmaRef="152" meaningRef="187" pos="ADV" wordRef="378">also</tei:seg>
          <tei:seg xml:id="KIH_90100430_1" type="token" lemmaRef="3595" meaningRef="5694" pos="ADJ ADV" wordRef="12536">lange</tei:seg>
          <tei:seg xml:id="KIH_90100430_2" type="pc">,</tei:seg>
          <tei:seg xml:id="KIH_90100430_3" type="token" lemmaRef="6687" meaningRef="14770" pos="PRP" wordRef="23379">unz</tei:seg>
          <tei:seg xml:id="KIH_90100430_4" type="token" lemmaRef="1517" meaningRef="2355" pos="PRO" wordRef="4999">er</tei:seg>
          <tei:seg xml:id="KIH_90100430_5" type="token" lemmaRef="6835" meaningRef="10895" pos="VRB" wordRef="23957">verdarp</tei:seg>
        </tei:l>
        <tei:l n="44">
          <tei:seg xml:id="KIH_90100440_0" type="token" lemmaRef="6467" meaningRef="10233" pos="CNJ" wordRef="22825">und</tei:seg>
          <tei:seg xml:id="KIH_90100440_1" type="token" lemmaRef="16981" meaningRef="29159" pos="ADV PRP GRA" wordRef="104873">zeiungist</tei:seg>
          <tei:seg xml:id="KIH_90100440_2" type="token" lemmaRef="2954" meaningRef="4746" pos="NOM" wordRef="10057">hungers</tei:seg>
          <tei:seg xml:id="KIH_90100440_3" type="token" lemmaRef="5752" meaningRef="9048" pos="VRB" wordRef="20239">starp</tei:seg>
          <tei:seg xml:id="KIH_90100440_4" type="pc">.</tei:seg>
        </tei:l>
        <tei:l n="45">
          <tei:seg xml:id="KIH_90100450_0" type="token" lemmaRef="1119" meaningRef="1770" pos="ART" wordRef="3507">der</tei:seg>
          <tei:seg xml:id="KIH_90100450_1" type="token" lemmaRef="6342" meaningRef="9997" pos="ADV PRP" wordRef="22503">uz</tei:seg>
          <tei:seg xml:id="KIH_90100450_2" type="token" lemmaRef="1119" meaningRef="1770" pos="ART" wordRef="3507">der</tei:seg>
          <tei:seg xml:id="KIH_90100450_3" type="token" lemmaRef="3913" meaningRef="6173" pos="NOM ADJ" wordRef="13666">maze</tei:seg>
          <tei:seg xml:id="KIH_90100450_4" type="token" lemmaRef="4872" meaningRef="7549" pos="NOM ADJ ADV" wordRef="78765">riche</tei:seg>
          <tei:seg xml:id="KIH_90100450_5" type="token" lemmaRef="3957" meaningRef="6236" pos="NOM" wordRef="13798">man</tei:seg>
          <tei:seg xml:id="KIH_90100450_6" type="pc">,</tei:seg>
        </tei:l>
        <tei:l n="46">
          <tei:seg xml:id="KIH_90100460_0" type="token" lemmaRef="1119" meaningRef="1770" pos="ART" wordRef="3510">des</tei:seg>
          <tei:seg xml:id="KIH_90100460_1" type="token" lemmaRef="21246" meaningRef="34904" pos="NOM" wordRef="172530">rihtum</tei:seg>
          <tei:seg xml:id="KIH_90100460_2" type="token" lemmaRef="4366" meaningRef="6823" pos="ADJ PRO NEG" wordRef="15237">niemen</tei:seg>
          <tei:seg xml:id="KIH_90100460_3" type="token" lemmaRef="99" meaningRef="132" pos="VRB" wordRef="239">geahten</tei:seg>
          <tei:seg xml:id="KIH_90100460_4" type="token" lemmaRef="3538" meaningRef="5605" pos="VRB VEM" wordRef="46333">chan</tei:seg>
          <tei:seg xml:id="KIH_90100460_5" type="pc">,</tei:seg>
        </tei:l>
        <tei:l n="47">
          <tei:seg xml:id="KIH_90100470_0" type="token" lemmaRef="1119" meaningRef="1770" pos="ART" wordRef="3504">dem</tei:seg>
          <tei:seg xml:id="KIH_90100470_1" type="token" lemmaRef="2066" meaningRef="3198" pos="VRB" wordRef="6962">gelichet</tei:seg>
          <tei:seg xml:id="KIH_90100470_2" type="token" lemmaRef="5445" meaningRef="8495" pos="PRO" wordRef="19017">sich</tei:seg>
          <tei:seg xml:id="KIH_90100470_3" type="token" lemmaRef="7643" meaningRef="12530" pos="POS" wordRef="27634">unser</tei:seg>
          <tei:seg xml:id="KIH_90100470_4" type="token" lemmaRef="6258" meaningRef="9871" pos="NOM" wordRef="172531">træhtin</tei:seg>
          <tei:seg xml:id="KIH_90100470_5" type="pc">.</tei:seg>
        </tei:l>
        <tei:l n="48">
          <tei:seg xml:id="KIH_90100480_0" type="token" lemmaRef="7608" meaningRef="12462" pos="ADV IPA" wordRef="27506">wie</tei:seg>
          <tei:seg xml:id="KIH_90100480_1" type="token" lemmaRef="4240" meaningRef="6635" pos="VRB VEM" wordRef="14770">moht</tei:seg>
          <tei:seg xml:id="KIH_90100480_2" type="token" lemmaRef="1517" meaningRef="2355" pos="PRO" wordRef="4999">er</tei:seg>
          <tei:seg xml:id="KIH_90100480_3" type="token" lemmaRef="3009" meaningRef="4813" pos="ADV" wordRef="10286">immer</tei:seg>
          <tei:seg xml:id="KIH_90100480_4" type="token" lemmaRef="4872" meaningRef="7549" pos="ADJ GRA" wordRef="16766">richer</tei:seg>
          <tei:seg xml:id="KIH_90100480_5" type="token" lemmaRef="5432" meaningRef="8479" pos="VRB VEX" wordRef="76844">sin</tei:seg>
          <tei:seg xml:id="KIH_90100480_6" type="pc">?</tei:seg>
        </tei:l>
        <tei:l n="49">
          <tei:seg xml:id="KIH_90100490_0" type="token" lemmaRef="1119" meaningRef="1770" pos="ART" wordRef="3506">den</tei:seg>
          <tei:seg xml:id="KIH_90100490_1" type="token" lemmaRef="3377" meaningRef="5319" pos="NOM" wordRef="46464">chneht</tei:seg>
          <tei:seg xml:id="KIH_90100490_2" type="pc">,</tei:seg>
          <tei:seg xml:id="KIH_90100490_3" type="token" lemmaRef="1119" meaningRef="1770" pos="ART" wordRef="3506">den</tei:seg>
          <tei:seg xml:id="KIH_90100490_4" type="token" lemmaRef="1517" meaningRef="2355" pos="PRO" wordRef="4999">er</tei:seg>
          <tei:seg xml:id="KIH_90100490_5" type="token" lemmaRef="3348" meaningRef="5256" pos="VRB" wordRef="172524">chleiden</tei:seg>
          <tei:seg xml:id="KIH_90100490_6" type="token" lemmaRef="2731" meaningRef="4403" pos="VRB" wordRef="9214">hiez</tei:seg>
          <tei:seg xml:id="KIH_90100490_7" type="pc">,</tei:seg>
        </tei:l>
        <tei:l n="50">
          <tei:seg xml:id="KIH_90100500_0" type="token" lemmaRef="6467" meaningRef="10233" pos="CNJ" wordRef="22825">und</tei:seg>
          <tei:seg xml:id="KIH_90100500_1" type="token" lemmaRef="1517" meaningRef="2355" pos="PRO" wordRef="4999">er</tei:seg>
          <tei:seg xml:id="KIH_90100500_2" type="token" lemmaRef="1517" meaningRef="2355" pos="POS PRO" wordRef="67997">sin</tei:seg>
          <tei:seg xml:id="KIH_90100500_3" type="token" lemmaRef="7487" meaningRef="12200" pos="NOM" wordRef="27038">werch</tei:seg>
          <tei:seg xml:id="KIH_90100500_4" type="token" lemmaRef="30703" meaningRef="48076" pos="ADV" wordRef="157718">darumbe</tei:seg>
          <tei:seg xml:id="KIH_90100500_5" type="token" lemmaRef="3567" meaningRef="5652" pos="VRB" wordRef="12445">liez</tei:seg>
          <tei:seg xml:id="KIH_90100500_6" type="pc">,</tei:seg>
        </tei:l>
        <tei:l n="51">
          <tei:seg xml:id="KIH_90100510_0" type="token" lemmaRef="1097" meaningRef="1741" pos="ART CNJ" wordRef="3398">daz</tei:seg>
          <tei:seg xml:id="KIH_90100510_1" type="token" lemmaRef="5432" meaningRef="8479" pos="VRB VEX" wordRef="18956">ist</tei:seg>
          <tei:seg xml:id="KIH_90100510_2" type="token" lemmaRef="1331" meaningRef="2068" pos="ART NUM" wordRef="4319">ein</tei:seg>
          <tei:seg xml:id="KIH_90100510_3" type="token" lemmaRef="1308" meaningRef="2042" pos="ADJ" wordRef="4246">edel</tei:seg>
          <tei:seg xml:id="KIH_90100510_4" type="token" lemmaRef="4872" meaningRef="7549" pos="NOM ADJ ADV" wordRef="78765">riche</tei:seg>
          <tei:seg xml:id="KIH_90100510_5" type="token" lemmaRef="3957" meaningRef="6236" pos="NOM" wordRef="13798">man</tei:seg>
          <tei:seg xml:id="KIH_90100510_6" type="pc">,</tei:seg>
        </tei:l>
        <tei:l n="52">
          <tei:seg xml:id="KIH_90100520_0" type="token" lemmaRef="1119" meaningRef="1770" pos="ART" wordRef="3506">den</tei:seg>
          <tei:seg xml:id="KIH_90100520_1" type="token" lemmaRef="2465" meaningRef="3951" pos="NOM" wordRef="8253">got</tei:seg>
          <tei:seg xml:id="KIH_90100520_2" type="token" lemmaRef="2598" meaningRef="77622" pos="VRB VEX" wordRef="8758">hat</tei:seg>
          <tei:seg xml:id="KIH_90100520_3" type="token" lemmaRef="7479" meaningRef="12173" pos="VRB" wordRef="26976">gewendet</tei:seg>
          <tei:seg xml:id="KIH_90100520_4" type="token" lemmaRef="199" meaningRef="38122" pos="PRP" wordRef="522">an</tei:seg>
        </tei:l>
        <tei:l n="53">
          <tei:seg xml:id="KIH_90100530_0" type="token" lemmaRef="1988" meaningRef="3058" pos="NOM" wordRef="6730">geburt</tei:seg>
          <tei:seg xml:id="KIH_90100530_1" type="token" lemmaRef="6467" meaningRef="10233" pos="CNJ" wordRef="22825">und</tei:seg>
          <tei:seg xml:id="KIH_90100530_2" type="token" lemmaRef="4873" meaningRef="7554" pos="NOM" wordRef="16775">richeit</tei:seg>
          <tei:seg xml:id="KIH_90100530_3" type="pc">.</tei:seg>
        </tei:l>
        <tei:l n="54">
          <tei:seg xml:id="KIH_90100540_0" type="token" lemmaRef="4172" meaningRef="6544" pos="PRP" wordRef="14531">mit</tei:seg>
          <tei:seg xml:id="KIH_90100540_1" type="token" lemmaRef="1119" meaningRef="1770" pos="ART" wordRef="3507">der</tei:seg>
          <tei:seg xml:id="KIH_90100540_2" type="token" lemmaRef="2534" meaningRef="4057" pos="ADJ" wordRef="8499">grozen</tei:seg>
          <tei:seg xml:id="KIH_90100540_3" type="token" lemmaRef="5283" meaningRef="8237" pos="NOM" wordRef="35306">schonheit</tei:seg>
        </tei:l>
        <tei:l n="55">
          <tei:seg xml:id="KIH_90100550_0" type="token" lemmaRef="7864" meaningRef="12897" pos="VRB" wordRef="28548">zieret</tei:seg>
          <tei:seg xml:id="KIH_90100550_1" type="token" lemmaRef="1517" meaningRef="2355" pos="PRO" wordRef="5008">in</tei:seg>
          <tei:seg xml:id="KIH_90100550_2" type="token" lemmaRef="2465" meaningRef="3951" pos="NOM" wordRef="8253">got</tei:seg>
          <tei:seg xml:id="KIH_90100550_3" type="token" lemmaRef="1055" meaningRef="1689" pos="ADV" wordRef="3258">dar</tei:seg>
          <tei:seg xml:id="KIH_90100550_4" type="token" lemmaRef="7770" meaningRef="12736" pos="PRP CNJ" wordRef="196209">zuo</tei:seg>
          <tei:seg xml:id="KIH_90100550_5" type="pc">,</tei:seg>
        </tei:l>
        <tei:l n="56">
          <tei:seg xml:id="KIH_90100560_0" type="token" lemmaRef="1097" meaningRef="1741" pos="ART CNJ" wordRef="3398">daz</tei:seg>
          <tei:seg xml:id="KIH_90100560_1" type="token" lemmaRef="1517" meaningRef="2355" pos="PRO" wordRef="4999">er</tei:seg>
          <tei:seg xml:id="KIH_90100560_2" type="token" lemmaRef="1125" meaningRef="1776" pos="ADV GRA" wordRef="3524">deste</tei:seg>
          <tei:seg xml:id="KIH_90100560_3" type="token" lemmaRef="414" meaningRef="562" pos="ADJ ADV GRA" wordRef="1102">baz</tei:seg>
          <tei:seg xml:id="KIH_90100560_4" type="token" lemmaRef="6301" meaningRef="9929" pos="VRB" wordRef="22322">tuo</tei:seg>
        </tei:l>
        <tei:l n="57">
          <tei:seg xml:id="KIH_90100570_0" type="token" lemmaRef="4172" meaningRef="6544" pos="PRP" wordRef="14531">mit</tei:seg>
          <tei:seg xml:id="KIH_90100570_1" type="token" lemmaRef="7487" meaningRef="12200" pos="NOM" wordRef="45212">werchen</tei:seg>
          <tei:seg xml:id="KIH_90100570_2" type="token" lemmaRef="6467" meaningRef="10233" pos="CNJ" wordRef="22825">und</tei:seg>
          <tei:seg xml:id="KIH_90100570_3" type="token" lemmaRef="4172" meaningRef="6544" pos="PRP" wordRef="14531">mit</tei:seg>
          <tei:seg xml:id="KIH_90100570_4" type="token" lemmaRef="2573" meaningRef="4120" pos="NOM ADJ ADV" wordRef="8634">guote</tei:seg>
          <tei:seg xml:id="KIH_90100570_5" type="pc">,</tei:seg>
        </tei:l>
        <tei:l n="58">
          <tei:seg xml:id="KIH_90100580_0" type="token" lemmaRef="4172" meaningRef="6544" pos="PRP" wordRef="14531">mit</tei:seg>
          <tei:seg xml:id="KIH_90100580_1" type="token" lemmaRef="3738" meaningRef="5924" pos="NOM" wordRef="13016">libe</tei:seg>
          <tei:seg xml:id="KIH_90100580_2" type="token" lemmaRef="6467" meaningRef="10233" pos="CNJ" wordRef="22825">und</tei:seg>
          <tei:seg xml:id="KIH_90100580_3" type="token" lemmaRef="4172" meaningRef="6544" pos="PRP" wordRef="14531">mit</tei:seg>
          <tei:seg xml:id="KIH_90100580_4" type="token" lemmaRef="4264" meaningRef="6672" pos="NOM" wordRef="14838">muote</tei:seg>
          <tei:seg xml:id="KIH_90100580_5" type="pc">.</tei:seg>
        </tei:l>
        <tei:l n="59">
          <tei:seg xml:id="KIH_90100590_0" type="token" lemmaRef="9329" meaningRef="15279" pos="CNJ" wordRef="32007">ob</tei:seg>
          <tei:seg xml:id="KIH_90100590_1" type="token" lemmaRef="1517" meaningRef="2355" pos="PRO" wordRef="4999">er</tei:seg>
          <tei:seg xml:id="KIH_90100590_2" type="token" lemmaRef="1055" meaningRef="1689" pos="ADV" wordRef="3258">dar</tei:seg>
          <tei:seg xml:id="KIH_90100590_3" type="token" lemmaRef="199" meaningRef="38122" pos="PRP" wordRef="522">an</tei:seg>
          <tei:seg xml:id="KIH_90100590_4" type="token" lemmaRef="6977" meaningRef="11256" pos="VRB" wordRef="24620">versumet</tei:seg>
          <tei:seg xml:id="KIH_90100590_5" type="token" lemmaRef="5445" meaningRef="8495" pos="PRO" wordRef="19017">sich</tei:seg>
          <tei:seg xml:id="KIH_90100590_6" type="pc">,</tei:seg>
        </tei:l>
        <tei:l n="60">
          <tei:seg xml:id="KIH_90100600_0" type="token" lemmaRef="1097" meaningRef="1741" pos="ART CNJ" wordRef="3398">daz</tei:seg>
          <tei:seg xml:id="KIH_90100600_1" type="token" lemmaRef="5432" meaningRef="8479" pos="VRB VEX" wordRef="18956">ist</tei:seg>
          <tei:seg xml:id="KIH_90100600_2" type="token" lemmaRef="148" meaningRef="183" pos="CNJ" wordRef="369">als</tei:seg>
          <tei:seg xml:id="KIH_90100600_3" type="token" lemmaRef="6466" meaningRef="14616" pos="ADJ ADV NEG" wordRef="151386">unpillich</tei:seg>
          <tei:seg xml:id="KIH_90100600_4" type="pc">,</tei:seg>
        </tei:l>
        <tei:l n="61">
          <tei:seg xml:id="KIH_90100610_0" type="token" lemmaRef="5601" meaningRef="8764" pos="ADV" wordRef="19596">so</tei:seg>
          <tei:seg xml:id="KIH_90100610_1" type="token" lemmaRef="1097" meaningRef="1741" pos="ART CNJ" wordRef="3398">daz</tei:seg>
          <tei:seg xml:id="KIH_90100610_2" type="token" lemmaRef="1119" meaningRef="1770" pos="ART" wordRef="3507">der</tei:seg>
          <tei:seg xml:id="KIH_90100610_3" type="token" lemmaRef="3377" meaningRef="5319" pos="NOM" wordRef="104773">chnecht</tei:seg>
          <tei:seg xml:id="KIH_90100610_4" type="token" lemmaRef="1517" meaningRef="2355" pos="POS PRO" wordRef="67997">sin</tei:seg>
          <tei:seg xml:id="KIH_90100610_5" type="token" lemmaRef="7487" meaningRef="12200" pos="NOM" wordRef="27038">werch</tei:seg>
          <tei:seg xml:id="KIH_90100610_6" type="token" lemmaRef="3567" meaningRef="5652" pos="VRB" wordRef="12444">lie</tei:seg>
          <tei:seg xml:id="KIH_90100610_7" type="pc">,</tei:seg>
        </tei:l>
        <tei:l n="62">
          <tei:seg xml:id="KIH_90100620_0" type="token" lemmaRef="1180" meaningRef="1864" pos="ADV" wordRef="3738">do</tei:seg>
          <tei:seg xml:id="KIH_90100620_1" type="token" lemmaRef="1517" meaningRef="2355" pos="PRO" wordRef="4999">er</tei:seg>
          <tei:seg xml:id="KIH_90100620_2" type="token" lemmaRef="5601" meaningRef="8764" pos="ADV" wordRef="19596">so</tei:seg>
          <tei:seg xml:id="KIH_90100620_3" type="token" lemmaRef="7677" meaningRef="12586" pos="NOM ADV" wordRef="27811">wol</tei:seg>
          <tei:seg xml:id="KIH_90100620_4" type="token" lemmaRef="3348" meaningRef="5256" pos="VRB" wordRef="46433">gechleidet</tei:seg>
          <tei:seg xml:id="KIH_90100620_5" type="token" lemmaRef="1844" meaningRef="2846" pos="VRB" wordRef="6313">gie</tei:seg>
          <tei:seg xml:id="KIH_90100620_6" type="pc">.</tei:seg>
        </tei:l>
        <tei:l n="63">
          <tei:seg xml:id="KIH_90100630_0" type="token" lemmaRef="148" meaningRef="183" pos="CNJ" wordRef="369">als</tei:seg>
          <tei:seg xml:id="KIH_90100630_1" type="token" lemmaRef="1517" meaningRef="2355" pos="PRO" wordRef="32780">im</tei:seg>
          <tei:seg xml:id="KIH_90100630_2" type="token" lemmaRef="2465" meaningRef="3951" pos="NOM" wordRef="8253">got</tei:seg>
          <tei:seg xml:id="KIH_90100630_3" type="token" lemmaRef="1139" meaningRef="1797" pos="ART" wordRef="3568">die</tei:seg>
          <tei:seg xml:id="KIH_90100630_4" type="token" lemmaRef="6294" meaningRef="9917" pos="NOM" wordRef="22261">tumpheit</tei:seg>
        </tei:l>
        <tei:l n="64">
          <tei:seg xml:id="KIH_90100640_0" type="token" lemmaRef="6687" meaningRef="14770" pos="PRP" wordRef="23379">unz</tei:seg>
          <tei:seg xml:id="KIH_90100640_1" type="token" lemmaRef="199" meaningRef="37996" pos="PRP" wordRef="522">an</tei:seg>
          <tei:seg xml:id="KIH_90100640_2" type="token" lemmaRef="1331" meaningRef="2068" pos="ART NUM" wordRef="4319">ein</tei:seg>
          <tei:seg xml:id="KIH_90100640_3" type="token" lemmaRef="1396" meaningRef="2156" pos="NOM" wordRef="4546">ende</tei:seg>
          <tei:seg xml:id="KIH_90100640_4" type="token" lemmaRef="6994" meaningRef="11295" pos="VRB" wordRef="286494">vertreit</tei:seg>
          <tei:seg xml:id="KIH_90100640_5" type="pc">,</tei:seg>
        </tei:l>
        <tei:l n="65">
          <tei:seg xml:id="KIH_90100650_0" type="token" lemmaRef="5601" meaningRef="8764" pos="ADV" wordRef="19596">so</tei:seg>
          <tei:seg xml:id="KIH_90100650_1" type="token" lemmaRef="4330" meaningRef="6767" pos="VRB" wordRef="15097">nimt</tei:seg>
          <tei:seg xml:id="KIH_90100650_2" type="token" lemmaRef="1517" meaningRef="2355" pos="PRO" wordRef="4999">er</tei:seg>
          <tei:seg xml:id="KIH_90100650_3" type="token" lemmaRef="1517" meaningRef="2355" pos="PRO" wordRef="32780">im</tei:seg>
          <tei:seg xml:id="KIH_90100650_4" type="token" lemmaRef="1517" meaningRef="2355" pos="POS PRO" wordRef="67997">sin</tei:seg>
          <tei:seg xml:id="KIH_90100650_5" type="token" lemmaRef="2573" meaningRef="13672" pos="NOM ADJ ADV" wordRef="42794">gut</tei:seg>
          <tei:seg xml:id="KIH_90100650_6" type="token" lemmaRef="2331" meaningRef="3733" pos="NOM" wordRef="7883">gwant</tei:seg>
          <tei:seg xml:id="KIH_90100650_7" type="pc">,</tei:seg>
        </tei:l>
        <tei:l n="66">
          <tei:seg xml:id="KIH_90100660_0" type="token" lemmaRef="3738" meaningRef="5924" pos="NOM" wordRef="13018">lip</tei:seg>
          <tei:seg xml:id="KIH_90100660_1" type="pc">,</tei:seg>
          <tei:seg xml:id="KIH_90100660_2" type="token" lemmaRef="3806" meaningRef="6009" pos="NOM" wordRef="256606">lute</tei:seg>
          <tei:seg xml:id="KIH_90100660_3" type="token" lemmaRef="6467" meaningRef="10233" pos="CNJ" wordRef="22825">und</tei:seg>
          <tei:seg xml:id="KIH_90100660_4" type="token" lemmaRef="3604" meaningRef="5708" pos="NOM" wordRef="12561">lant</tei:seg>
          <tei:seg xml:id="KIH_90100660_5" type="pc">.</tei:seg>
        </tei:l>
        <tei:l n="67">
          <tei:seg xml:id="KIH_90100670_0" type="token" lemmaRef="1055" meaningRef="1689" pos="ADV" wordRef="3258">dar</tei:seg>
          <tei:seg xml:id="KIH_90100670_1" type="token" lemmaRef="7770" meaningRef="12736" pos="PRP CNJ" wordRef="31260">zu</tei:seg>
          <tei:seg xml:id="KIH_90100670_2" type="token" lemmaRef="7490" meaningRef="12210" pos="VRB" wordRef="27082">werfet</tei:seg>
          <tei:seg xml:id="KIH_90100670_3" type="token" lemmaRef="1517" meaningRef="2355" pos="PRO" wordRef="4999">er</tei:seg>
          <tei:seg xml:id="KIH_90100670_4" type="token" lemmaRef="1517" meaningRef="2355" pos="PRO" wordRef="5008">in</tei:seg>
        </tei:l>
        <tei:l n="68">
          <tei:seg xml:id="KIH_90100680_0" type="token" lemmaRef="3028" meaningRef="4834" pos="PRP" wordRef="10369">in</tei:seg>
          <tei:seg xml:id="KIH_90100680_1" type="token" lemmaRef="1517" meaningRef="2355" pos="POS" wordRef="5023">sinen</tei:seg>
          <tei:seg xml:id="KIH_90100680_2" type="token" lemmaRef="3241" meaningRef="5104" pos="NOM" wordRef="104807">charchære</tei:seg>
          <tei:seg xml:id="KIH_90100680_3" type="token" lemmaRef="2837" meaningRef="4558" pos="ADV" wordRef="9597">hin</tei:seg>
          <tei:seg xml:id="KIH_90100680_4" type="pc">,</tei:seg>
        </tei:l>
        <tei:l n="69">
          <tei:seg xml:id="KIH_90100690_0" type="token" lemmaRef="1055" meaningRef="1689" pos="ADV CNJ" wordRef="3255">da</tei:seg>
          <tei:seg xml:id="KIH_90100690_1" type="token" lemmaRef="1517" meaningRef="2355" pos="PRO" wordRef="4999">er</tei:seg>
          <tei:seg xml:id="KIH_90100690_2" type="token" lemmaRef="3009" meaningRef="4813" pos="ADV" wordRef="10286">immer</tei:seg>
          <tei:seg xml:id="KIH_90100690_3" type="token" lemmaRef="4238" meaningRef="82702" pos="VRB VEM" wordRef="14740">muoz</tei:seg>
          <tei:seg xml:id="KIH_90100690_4" type="token" lemmaRef="870" meaningRef="1431" pos="VRB" wordRef="2754">brinnen</tei:seg>
          <tei:seg xml:id="KIH_90100690_5" type="pc">.</tei:seg>
        </tei:l>
        <tei:l n="70">
          <tei:seg xml:id="KIH_90100700_0" type="token" lemmaRef="56117" meaningRef="90961" pos="PRO" wordRef="304747">ir</tei:seg>
          <tei:seg xml:id="KIH_90100700_1" type="token" lemmaRef="4240" meaningRef="6637" pos="VRB VEM" wordRef="14789">mugt</tei:seg>
          <tei:seg xml:id="KIH_90100700_2" type="token" lemmaRef="56117" meaningRef="90961" pos="PRO" wordRef="304933">iuch</tei:seg>
          <tei:seg xml:id="KIH_90100700_3" type="token" lemmaRef="7677" meaningRef="12586" pos="NOM ADV" wordRef="27811">wol</tei:seg>
          <tei:seg xml:id="KIH_90100700_4" type="token" lemmaRef="6950" meaningRef="11189" pos="VRB" wordRef="24496">versinnen</tei:seg>
          <tei:seg xml:id="KIH_90100700_5" type="pc">:</tei:seg>
        </tei:l>
        <tei:l n="71">
          <tei:seg xml:id="KIH_90100710_0" type="token" lemmaRef="1055" meaningRef="1689" pos="ADV CNJ" wordRef="3255">da</tei:seg>
          <tei:seg xml:id="KIH_90100710_1" type="token" lemmaRef="1331" meaningRef="2068" pos="ART NUM" wordRef="4319">ein</tei:seg>
          <tei:seg xml:id="KIH_90100710_2" type="token" lemmaRef="2684" meaningRef="4322" pos="NOM" wordRef="9039">herre</tei:seg>
          <tei:seg xml:id="KIH_90100710_3" type="token" lemmaRef="1517" meaningRef="2355" pos="POS" wordRef="5023">sinen</tei:seg>
          <tei:seg xml:id="KIH_90100710_4" type="token" lemmaRef="5555" meaningRef="8680" pos="NOM" wordRef="172532">sluzel</tei:seg>
          <tei:seg xml:id="KIH_90100710_5" type="token" lemmaRef="4330" meaningRef="6767" pos="VRB" wordRef="15097">nimt</tei:seg>
        </tei:l>
        <tei:l n="72">
          <tei:seg xml:id="KIH_90100720_0" type="token" lemmaRef="6467" meaningRef="10233" pos="CNJ" wordRef="22825">und</tei:seg>
          <tei:seg xml:id="KIH_90100720_1" type="token" lemmaRef="646" meaningRef="1027" pos="VRB" wordRef="88754">bevilhet</tei:seg>
          <tei:seg xml:id="KIH_90100720_2" type="token" lemmaRef="1517" meaningRef="2355" pos="PRO" wordRef="5008">in</tei:seg>
          <tei:seg xml:id="KIH_90100720_3" type="token" lemmaRef="1119" meaningRef="1770" pos="ART" wordRef="3504">dem</tei:seg>
          <tei:seg xml:id="KIH_90100720_4" type="pc">,</tei:seg>
          <tei:supplied>
            <tei:seg xml:id="KIH_90100720_5" type="token" lemmaRef="1119" meaningRef="1770" pos="ART" wordRef="3507">der</tei:seg>
          </tei:supplied>
          <tei:seg xml:id="KIH_90100720_6" type="token" lemmaRef="1517" meaningRef="2355" pos="PRO" wordRef="32780">im</tei:seg>
          <tei:seg xml:id="KIH_90100720_7" type="token" lemmaRef="2362" meaningRef="3807" pos="VRB" wordRef="7997">gezimt</tei:seg>
          <tei:seg xml:id="KIH_90100720_8" type="pc">;</tei:seg>
        </tei:l>
        <tei:l n="73">
          <tei:seg xml:id="KIH_90100730_0" type="token" lemmaRef="5432" meaningRef="8479" pos="VRB VEX" wordRef="18956">ist</tei:seg>
          <tei:seg xml:id="KIH_90100730_1" type="token" lemmaRef="1119" meaningRef="1770" pos="ART" wordRef="3507">der</tei:seg>
          <tei:seg xml:id="KIH_90100730_2" type="token" lemmaRef="3377" meaningRef="5319" pos="NOM" wordRef="46464">chneht</tei:seg>
          <tei:seg xml:id="KIH_90100730_3" type="token" lemmaRef="5601" meaningRef="8764" pos="ADV" wordRef="19596">so</tei:seg>
          <tei:seg xml:id="KIH_90100730_4" type="token" lemmaRef="2108" meaningRef="3266" pos="ADJ" wordRef="7116">gemuot</tei:seg>
          <tei:seg xml:id="KIH_90100730_5" type="pc">,</tei:seg>
        </tei:l>
        <tei:l n="74">
          <tei:seg xml:id="KIH_90100740_0" type="token" lemmaRef="1097" meaningRef="1741" pos="ART CNJ" wordRef="3398">daz</tei:seg>
          <tei:seg xml:id="KIH_90100740_1" type="token" lemmaRef="1517" meaningRef="2355" pos="PRO" wordRef="4999">er</tei:seg>
          <tei:seg xml:id="KIH_90100740_2" type="token" lemmaRef="8700" meaningRef="13698" pos="NOM PRO" wordRef="30236">sines</tei:seg>
          <tei:seg xml:id="KIH_90100740_3" type="token" lemmaRef="2684" meaningRef="4322" pos="NOM" wordRef="9040">herren</tei:seg>
          <tei:seg xml:id="KIH_90100740_4" type="token" lemmaRef="2573" meaningRef="4120" pos="NOM ADJ ADV" wordRef="8633">guot</tei:seg>
        </tei:l>
        <tei:l n="75">
          <tei:seg xml:id="KIH_90100750_0" type="token" lemmaRef="655" meaningRef="1045" pos="VRB" wordRef="1977">bewart</tei:seg>
          <tei:seg xml:id="KIH_90100750_1" type="token" lemmaRef="4172" meaningRef="6544" pos="PRP" wordRef="14531">mit</tei:seg>
          <tei:seg xml:id="KIH_90100750_2" type="token" lemmaRef="14777" meaningRef="9801" pos="NOM ADJ NEG" wordRef="61800">untriwen</tei:seg>
          <tei:seg xml:id="KIH_90100750_3" type="pc">;</tei:seg>
        </tei:l>
        <tei:l n="76">
          <tei:seg xml:id="KIH_90100760_0" type="token" lemmaRef="1097" meaningRef="1741" pos="ART CNJ" wordRef="3398">daz</tei:seg>
          <tei:seg xml:id="KIH_90100760_1" type="token" lemmaRef="4240" meaningRef="6635" pos="VRB VEM" wordRef="14749">mag</tei:seg>
          <tei:seg xml:id="KIH_90100760_2" type="token" lemmaRef="1517" meaningRef="2355" pos="PRO" wordRef="4999">er</tei:seg>
          <tei:seg xml:id="KIH_90100760_3" type="token" lemmaRef="5601" meaningRef="8764" pos="ADV" wordRef="19596">so</tei:seg>
          <tei:seg xml:id="KIH_90100760_4" type="token" lemmaRef="1136" meaningRef="1789" pos="ADJ ADV" wordRef="42297">diche</tei:seg>
          <tei:seg xml:id="KIH_90100760_5" type="token" lemmaRef="62848" meaningRef="99542" pos="VRB" wordRef="328011">irniwen</tei:seg>
          <tei:seg xml:id="KIH_90100760_6" type="pc">,</tei:seg>
        </tei:l>
        <tei:l n="77">
          <tei:seg xml:id="KIH_90100770_0" type="token" lemmaRef="6687" meaningRef="14770" pos="PRP" wordRef="23379">unz</tei:seg>
          <tei:seg xml:id="KIH_90100770_1" type="token" lemmaRef="1517" meaningRef="2355" pos="PRO" wordRef="4999">er</tei:seg>
          <tei:seg xml:id="KIH_90100770_2" type="token" lemmaRef="1055" meaningRef="1689" pos="ADV CNJ" wordRef="3255">da</tei:seg>
          <tei:seg xml:id="KIH_90100770_3" type="token" lemmaRef="7193" meaningRef="11656" pos="PRP" wordRef="25544">von</tei:seg>
          <tei:seg xml:id="KIH_90100770_4" type="token" lemmaRef="6974" meaningRef="11247" pos="VRB" wordRef="64770">verstozen</tei:seg>
          <tei:seg xml:id="KIH_90100770_5" type="token" lemmaRef="7489" meaningRef="12208" pos="VRB VEX" wordRef="27059">wirt</tei:seg>
        </tei:l>
        <tei:l n="78">
          <tei:seg xml:id="KIH_90100780_0" type="token" lemmaRef="6467" meaningRef="10233" pos="CNJ" wordRef="22825">und</tei:seg>
          <tei:seg xml:id="KIH_90100780_1" type="token" lemmaRef="8700" meaningRef="13698" pos="NOM PRO" wordRef="30236">sines</tei:seg>
          <tei:seg xml:id="KIH_90100780_2" type="token" lemmaRef="2684" meaningRef="4322" pos="NOM" wordRef="9040">herren</tei:seg>
          <tei:seg xml:id="KIH_90100780_3" type="token" lemmaRef="2950" meaningRef="4740" pos="NOM" wordRef="10046">hulde</tei:seg>
          <tei:seg xml:id="KIH_90100780_4" type="token" lemmaRef="30771" meaningRef="48193" pos="NEG VRB" wordRef="158352">enbirt</tei:seg>
        </tei:l>
        <tei:l n="79">
          <tei:seg xml:id="KIH_90100790_0" type="token" lemmaRef="7193" meaningRef="11656" pos="PRP" wordRef="25544">von</tei:seg>
          <tei:seg xml:id="KIH_90100790_1" type="token" lemmaRef="5332" meaningRef="8328" pos="NOM ADJ" wordRef="18557">schulden</tei:seg>
          <tei:seg xml:id="KIH_90100790_2" type="token" lemmaRef="3009" meaningRef="4813" pos="ADV" wordRef="10286">immer</tei:seg>
          <tei:seg xml:id="KIH_90100790_3" type="token" lemmaRef="4034" meaningRef="6338" pos="NOM ADJ ADV GRA" wordRef="38738">mere</tei:seg>
          <tei:seg xml:id="KIH_90100790_4" type="pc">.</tei:seg>
        </tei:l>
        <tei:l n="80">
          <tei:seg xml:id="KIH_90100800_0" type="token" lemmaRef="1331" meaningRef="2068" pos="ART NUM" wordRef="4319">ein</tei:seg>
          <tei:seg xml:id="KIH_90100800_1" type="token" lemmaRef="5601" meaningRef="8764" pos="ADV" wordRef="19596">so</tei:seg>
          <tei:seg xml:id="KIH_90100800_2" type="token" lemmaRef="6301" meaningRef="9929" pos="VRB" wordRef="22297">getan</tei:seg>
          <tei:seg xml:id="KIH_90100800_3" type="token" lemmaRef="6502" meaningRef="10321" pos="NEG VRB" wordRef="22928">unere</tei:seg>
        </tei:l>
        <tei:l n="81">
          <tei:seg xml:id="KIH_90100810_0" type="token" lemmaRef="4238" meaningRef="82702" pos="VRB VEM" wordRef="42698">muz</tei:seg>
          <tei:seg xml:id="KIH_90100810_1" type="token" lemmaRef="3006" meaningRef="15705" pos="ADJ" wordRef="95591">igelichem</tei:seg>
          <tei:seg xml:id="KIH_90100810_2" type="token" lemmaRef="3957" meaningRef="6236" pos="NOM" wordRef="13798">man</tei:seg>
          <tei:seg xml:id="KIH_90100810_3" type="token" lemmaRef="2199" meaningRef="3477" pos="VRB" wordRef="7454">geschehen</tei:seg>
          <tei:seg xml:id="KIH_90100810_4" type="pc">,</tei:seg>
        </tei:l>
        <tei:l n="82">
          <tei:seg xml:id="KIH_90100820_0" type="token" lemmaRef="1119" meaningRef="1770" pos="ART" wordRef="3506">den</tei:seg>
          <tei:seg xml:id="KIH_90100820_1" type="token" lemmaRef="2465" meaningRef="3951" pos="NOM" wordRef="8253">got</tei:seg>
          <tei:seg xml:id="KIH_90100820_2" type="token" lemmaRef="1095" meaningRef="1739" pos="PRP" wordRef="44084">darzu</tei:seg>
          <tei:seg xml:id="KIH_90100820_3" type="token" lemmaRef="2598" meaningRef="77622" pos="VRB VEX" wordRef="8758">hat</tei:seg>
          <tei:seg xml:id="KIH_90100820_4" type="token" lemmaRef="1645" meaningRef="2567" pos="VRB" wordRef="5591">ersehen</tei:seg>
          <tei:seg xml:id="KIH_90100820_5" type="pc">,</tei:seg>
        </tei:l>
        <tei:l n="83">
          <tei:seg xml:id="KIH_90100830_0" type="token" lemmaRef="1097" meaningRef="1741" pos="ART CNJ" wordRef="3398">daz</tei:seg>
          <tei:seg xml:id="KIH_90100830_1" type="token" lemmaRef="1517" meaningRef="2355" pos="PRO" wordRef="4999">er</tei:seg>
          <tei:seg xml:id="KIH_90100830_2" type="token" lemmaRef="1517" meaningRef="2355" pos="PRO" wordRef="32780">im</tei:seg>
          <tei:seg xml:id="KIH_90100830_3" type="token" lemmaRef="646" meaningRef="1029" pos="VRB" wordRef="88754">bevilhet</tei:seg>
          <tei:seg xml:id="KIH_90100830_4" type="token" lemmaRef="21246" meaningRef="34904" pos="NOM" wordRef="116584">rihtuom</tei:seg>
          <tei:seg xml:id="KIH_90100830_5" type="pc">.</tei:seg>
        </tei:l>
        <tei:l n="84">
          <tei:seg xml:id="KIH_90100840_0" type="token" lemmaRef="7473" meaningRef="12160" pos="VRB VEM" wordRef="26922">wil</tei:seg>
          <tei:seg xml:id="KIH_90100840_1" type="token" lemmaRef="1517" meaningRef="2355" pos="PRO" wordRef="4999">er</tei:seg>
          <tei:seg xml:id="KIH_90100840_2" type="token" lemmaRef="1119" meaningRef="1770" pos="ART" wordRef="3506">den</tei:seg>
          <tei:seg xml:id="KIH_90100840_3" type="token" lemmaRef="1292" meaningRef="2021" pos="ADJ" wordRef="4211">ewigen</tei:seg>
          <tei:seg xml:id="KIH_90100840_4" type="token" lemmaRef="5030" meaningRef="7812" pos="NOM" wordRef="17418">ruom</tei:seg>
        </tei:l>
        <tei:l n="85">
          <tei:seg xml:id="KIH_90100850_0" type="token" lemmaRef="1055" meaningRef="1689" pos="ADV CNJ" wordRef="3255">da</tei:seg>
          <tei:seg xml:id="KIH_90100850_1" type="token" lemmaRef="4172" meaningRef="6544" pos="PRP" wordRef="14531">mit</tei:seg>
          <tei:seg xml:id="KIH_90100850_2" type="token" lemmaRef="4377" meaningRef="6838" pos="ADJ ADV NEG" wordRef="15286">niht</tei:seg>
          <tei:seg xml:id="KIH_90100850_3" type="token" lemmaRef="2348" meaningRef="3773" pos="VRB" wordRef="7932">gewinnen</tei:seg>
          <tei:seg xml:id="KIH_90100850_4" type="pc">;</tei:seg>
        </tei:l>
        <tei:l n="86">
          <tei:seg xml:id="KIH_90100860_0" type="token" lemmaRef="5601" meaningRef="8764" pos="ADV" wordRef="19596">so</tei:seg>
          <tei:seg xml:id="KIH_90100860_1" type="token" lemmaRef="1119" meaningRef="1770" pos="ART" wordRef="3510">des</tei:seg>
          <tei:seg xml:id="KIH_90100860_2" type="token" lemmaRef="2465" meaningRef="3951" pos="NOM" wordRef="8253">got</tei:seg>
          <tei:seg xml:id="KIH_90100860_3" type="token" lemmaRef="7489" meaningRef="16763" pos="VRB VEX" wordRef="27059">wirt</tei:seg>
          <tei:seg xml:id="KIH_90100860_4" type="token" lemmaRef="3039" meaningRef="4847" pos="ADV" wordRef="10398">innen</tei:seg>
          <tei:seg xml:id="KIH_90100860_5" type="pc">,</tei:seg>
        </tei:l>
        <tei:l n="87">
          <tei:seg xml:id="KIH_90100870_0" type="token" lemmaRef="1097" meaningRef="1741" pos="ART CNJ" wordRef="3398">daz</tei:seg>
          <tei:seg xml:id="KIH_90100870_1" type="token" lemmaRef="1517" meaningRef="2355" pos="PRO" wordRef="4999">er</tei:seg>
          <tei:seg xml:id="KIH_90100870_2" type="token" lemmaRef="5601" meaningRef="8764" pos="ADV" wordRef="19596">so</tei:seg>
          <tei:seg xml:id="KIH_90100870_3" type="token" lemmaRef="6295" meaningRef="14565" pos="ADJ ADV" wordRef="67297">tumplichen</tei:seg>
          <tei:seg xml:id="KIH_90100870_4" type="token" lemmaRef="6301" meaningRef="9929" pos="VRB" wordRef="22331">tuot</tei:seg>
          <tei:seg xml:id="KIH_90100870_5" type="pc">;</tei:seg>
        </tei:l>
        <tei:l n="88">
          <tei:seg xml:id="KIH_90100880_0" type="token" lemmaRef="2465" meaningRef="3951" pos="NOM" wordRef="8256">gotes</tei:seg>
          <tei:seg xml:id="KIH_90100880_1" type="token" lemmaRef="2950" meaningRef="4742" pos="NOM" wordRef="10046">hulde</tei:seg>
          <tei:seg xml:id="KIH_90100880_2" type="token" lemmaRef="6467" meaningRef="10233" pos="CNJ" wordRef="22825">und</tei:seg>
          <tei:seg xml:id="KIH_90100880_3" type="token" lemmaRef="2573" meaningRef="4120" pos="NOM ADJ ADV" wordRef="8633">guot</tei:seg>
        </tei:l>
        <tei:l n="89">
          <tei:seg xml:id="KIH_90100890_0" type="token" lemmaRef="2598" meaningRef="77622" pos="VRB VEX" wordRef="8758">hat</tei:seg>
          <tei:seg xml:id="KIH_90100890_1" type="token" lemmaRef="1517" meaningRef="2355" pos="PRO" wordRef="4999">er</tei:seg>
          <tei:seg xml:id="KIH_90100890_2" type="token" lemmaRef="16981" meaningRef="29159" pos="ADV PRP GRA" wordRef="104873">zeiungist</tei:seg>
          <tei:seg xml:id="KIH_90100890_3" type="token" lemmaRef="6888" meaningRef="11018" pos="VRB" wordRef="24242">verlorn</tei:seg>
          <tei:seg xml:id="KIH_90100890_4" type="pc">.</tei:seg>
        </tei:l>
        <tei:l n="90">
          <tei:seg xml:id="KIH_90100900_0" type="token" lemmaRef="7505" meaningRef="12246" pos="VRB" wordRef="273614">wær</tei:seg>
          <tei:seg xml:id="KIH_90100900_1" type="token" lemmaRef="1517" meaningRef="2355" pos="PRO" wordRef="4999">er</tei:seg>
          <tei:seg xml:id="KIH_90100900_2" type="token" lemmaRef="1073" meaningRef="1716" pos="ADV" wordRef="3323">danne</tei:seg>
          <tei:seg xml:id="KIH_90100900_3" type="token" lemmaRef="4365" meaningRef="6822" pos="ADV NEG" wordRef="15230">nie</tei:seg>
          <tei:seg xml:id="KIH_90100900_4" type="token" lemmaRef="1964" meaningRef="3014" pos="VRB" wordRef="6656">geborn</tei:seg>
          <tei:seg xml:id="KIH_90100900_5" type="pc">,</tei:seg>
        </tei:l>
        <tei:l n="91">
          <tei:seg xml:id="KIH_90100910_0" type="token" lemmaRef="1119" meaningRef="1770" pos="ART" wordRef="3510">des</tei:seg>
          <tei:seg xml:id="KIH_90100910_1" type="token" lemmaRef="7505" meaningRef="12246" pos="VRB" wordRef="273619">wære</tei:seg>
          <tei:seg xml:id="KIH_90100910_2" type="token" lemmaRef="1517" meaningRef="2355" pos="POS" wordRef="5024">siner</tei:seg>
          <tei:seg xml:id="KIH_90100910_3" type="token" lemmaRef="5349" meaningRef="8359" pos="NOM" wordRef="18609">sele</tei:seg>
          <tei:seg xml:id="KIH_90100910_4" type="token" lemmaRef="4400" meaningRef="6863" pos="NOM" wordRef="79200">not</tei:seg>
          <tei:seg xml:id="KIH_90100910_5" type="pc">,</tei:seg>
        </tei:l>
        <tei:l n="92">
          <tei:seg xml:id="KIH_90100920_0" type="token" lemmaRef="7387" meaningRef="12001" pos="CNJ" wordRef="287445">wan</tei:seg>
          <tei:seg xml:id="KIH_90100920_1" type="token" lemmaRef="1139" meaningRef="1797" pos="ART" wordRef="45021">diu</tei:seg>
          <tei:seg xml:id="KIH_90100920_2" type="token" lemmaRef="5432" meaningRef="8479" pos="VRB VEX" wordRef="18956">ist</tei:seg>
          <tei:seg xml:id="KIH_90100920_3" type="token" lemmaRef="1293" meaningRef="2022" pos="ADJ ADV" wordRef="137730">ewichlichen</tei:seg>
          <tei:seg xml:id="KIH_90100920_4" type="token" lemmaRef="6118" meaningRef="9650" pos="NOM ADJ" wordRef="68170">tot</tei:seg>
          <tei:seg xml:id="KIH_90100920_5" type="pc">.</tei:seg>
        </tei:l>
      </tei:p>
    </tei:body>
  </tei:text>
</tei:TEI>
